Workbook

Sheet 基本入力
B1: 契約書作成入力フォーム
B3: 入力方法 水色 とピンク の項目を埋めていきましょう。ピンクはプルダウンで選択、当てはまるものがない場合は手入力も出来ます。グレー は自動的に反映しますが、自動反映する内容と違うときは手入力しましょう。 色がついている項目 タブの色と、各書類に必要な項目の色が同じ色になっています。例えば媒介 と約定 だけ作る場合は、オレンジと緑の項目を入力しましょう。 売契について 業者用と個人用は、契約不適合の期間が違うので要注意！誤って印刷しないように、使わないタブは、右クリックして、グレーに変更しておくとよいでしょう。ちなみに一般法人は､物件の契約不適合の期間は宅建業者と同じですが、設備の契約不適合責任を負いません。
B11: ↓住所の番地は●番●にすること。壁芯面積は、東京カンテイがない場合は入れませんが、売主から入れてほしいと言われたら入れてあげましょう。
B13: 買主 | F13: ●買主太郎 | X13: 物件名 | AS13: ● | AV13: 号室
B15: 住居表示 | F15: 東京都 | J15: 練馬区 | N15: 高松3丁目 | X15: ●番● | AB15: ="-"&AS13&"号" -> -●号 | AG15: 間取り | AJ15: ● | AL15: ＬＤＫ | AP15: 壁芯 | AS15: - | AV15: ㎡
B18: □ | C18: オートロックの時はチェック | M18: 売契 一通作成、二通作成、電子契約 を選択 | AB18: 一通作成 | AG18: 印紙代が 買主負担じゃない時 は選択 | AT18: 買主負担
B21: ↓ここからは謄本を見ていれます。謄本に物件名がない場合は、「建物の名称」の物件名の後に（登記記録上記載なし）」と付け足しておきましょう。 抵当権、賃借権などがある場合は、重説「1.登記記録に記録された事項」でいれてください。 | AY21: 延床計算用
AY23: 1
B24: 一棟の建物の表示 | F24: 所在 | J24: =J15&N15 -> 練馬区高松3丁目 | AB24: ● | AD24: 番地 | AG24: ● | AY24: 2
AY25: 3
F26: 建物の名称 | J26: =AB13 -> 0 | AY26: 4
AY27: 5
F28: 構造 | J28: 鉄筋コンクリート造陸屋根●階建 | AB28: 延床面積 | AF28: ● | AK28: ㎡ | AM28: ←延床面積は謄本には記載がないので、右の「延床計算用」表に各階の面積を入力していき、オートSUMで合計していれます。 | AY28: 6
AY29: 7
B30: 専有部分の建物の表示 | F30: 家屋番号 | J30: =N15 -> 高松3丁目 | R30: =AB24&"番"&AG24&"の" -> ●番●の | X30: ● | AB30: 建物の名称 | AF30: ● | AY30: 8
AY31: 9
F32: 種類 | J32: 居宅 | N32: 構造 | Q32: ●鉄筋コンクリート造1階建 | AH32: ● | AJ32: 階部分 | AY32: 10
AY33: 11
F34: 登記簿面積 | O34: ㎡ | Q34: 建築時期 | Z34: 年 | AD34: 月 | AH34: 日新築 | AY34: 12
AY35: 13
AY36: 14
B37: 売主 | F37: ●登記名義人 | U37: 売主 登記簿住所 | AB37: ●登記名義人住所 | AY37: 15
AY38: 16
AY39: 17
B40: 土地 | D40: 番号 | F40: 所在 | U40: 地番 | Y40: 地目 | AB40: 地積 | AG40: 権利の種類 | AL40: 権利の割合
D42: 1 | F42: =$J$15&$N$15 -> 練馬区高松3丁目 | U42: =AB24&"番"&AG24 -> ●番● | Y42: 宅地 | AB42: ● | AF42: ㎡ | AR42: 分の
D44: 2 | AF44: ㎡ | AR44: 分の
D46: 3 | AF46: ㎡ | AR46: 分の
D48: 4 | AF48: ㎡ | AR48: 分の
D50: 5 | AF50: ㎡ | AR50: 分の
D52: 6 | AF52: ㎡ | AR52: 分の
D54: 敷地権登記がなければ■無にする→ | R54: ■ | S54: 有 | U54: ・ | V54: □ | W54: 無 | Y54: 合計 | AB54: =COUNTA(AB42:AE53) -> 1 | AE54: 筆 | AG54: =SUM(AB42:AE53) -> 0 | AK54: ㎡ | AL54: 実測面積 | AR54: - | AW54: ㎡
B57: □ | C57: ←譲渡承諾特約がある場合はチェック。（引渡日を自動で解除期日に設定する。）地上権の場合は譲渡承諾いらないのでチェック不要。
B59: □ | C59: 旧法借地権（平成4年7月31日以前） | O59: □ | P59: 新法借地権（平成4年８月1日以降） | AB59: 新法なら、どちらかにチェック→ | AL59: □ | AM59: 普通借地権 | AR59: □ | AS59: 定期借地権
B61: 借地対象面積 | M61: ㎡ | O61: □ | P61: 登記簿 | S61: □ | T61: 実測 | V61: 地代 | X61: 月額 | AD61: 円 | AP61: ←堅固建物所有にする （木造等は非堅固建物）
B63: 貸主住所 | AJ63: 氏名
B65: 借地期間 | P65: 年 | T65: 月 | X65: 日 | Z65: ～ | AH65: 年 | AL65: 月 | AP65: 日まで | AU65: 年間
B68: ここからの太枠の項目を、契発を見て入れます。業者情報と消費税額は、売主からの連絡を待ちましょう。
B70: 契約日 | F70: 令和 | I70: 8 | K70: 年 | O70: 月 | S70: 日 | V70: 物件価格 | AH70: 円 | AK70: 本体価格 | AO70: =AA70-AA74 -> 0 | AV70: 円
B72: 媒介期限 | F72: 令和 | I72: =IF(AND(M70>=1,M70<=9),I70,I70+1) -> 9 | K72: 年 | M72: =IF(AND(M70>=1,M70<=9),M70+3,M70-9) -> -9 | O72: 月 | Q72: =IF(Q70="","",Q70-1) | S72: 日 | V72: 手付金 | AH72: 円 | AK72: 土地価格 | AV72: 円
B74: ↑契約日の日にちが1日の場合は、媒介期限は３か月後の日付で手入力しましょう。 | V74: 消費税 | AH74: 円 | AK74: 建物価格 | AV74: 円
AY75: 国土交通大臣
AY76: 東京都知事
V77: 仲介手数料計算用 ※イレギュラーの時以外は入力しない | AY77: 神奈川県知事
E78: 売 主 | M78: 買 主 | AY78: 茨城県知事
V79: 番号を選択 | AB79: 仲介手数料計算式 | AK79: 仲介手数料額 | AP79: 手数料率 | AS79: ６万円 | AV79: 税 | AY79: 栃木県知事
B80: 番号 | M80: ② | AY80: 群馬県知事
V81: ① | X81: 消費税なし | AB81: 本体価格×3%+6万円 | AK81: =ROUNDDOWN((AO70*AP81)+AS81,0) -> 60000 | AP81: 0.03 | AS81: 60000 | AY81: 埼玉県知事
B82: 手数料 | E82: =IF(E80="","",VLOOKUP(E80,V81:AJ94,7)) | M82: =IF(M80="","",VLOOKUP(M80,V81:AJ94,7)) -> （本体価格×3％＋6万円）×消費税 | AY82: 千葉県知事
V83: ② | X83: 正規 | AB83: （本体価格×3％＋6万円）×消費税 | AK83: =ROUNDDOWN(((AO70*AP83)+AS83)*AV83,0) -> 66000 | AP83: 0.03 | AS83: 60000 | AV83: 1.1
B84: 仲手 | E84: =IFERROR(IF(E80="","",VLOOKUP(E80,V81:AO94,16))-E86,"") | K84: 円 | M84: =IFERROR(IF(M80="","",VLOOKUP(M80,V81:AO94,16))-M86,"") -> 66000 | S84: 円
V85: ③ | X85: ３%税込 | AB85: 本体価格×3%（税込） | AK85: =ROUNDDOWN(AO70*AP85,0) -> 0 | AP85: 0.03
B86: 値引 | E86: 0 | K86: 円 | S86: 円 | AY86: ■売主宅建士の地域
V87: ④ | X87: ３%税別 | AB87: （本体価格×3%）×消費税 | AK87: =ROUNDDOWN(AO70*AP87*AV87,0) -> 0 | AP87: 0.03 | AV87: 1.1 | AY87: ( 東京 )
B88: 消費税 | E88: =IFERROR(E84-ROUNDUP(E84/1.1,0),"") | K88: 円 | M88: =IFERROR(M84-ROUNDUP(M84/1.1,0),"") -> 6000 | S88: 円 | AY88: ( 神奈川 )
V89: ⑤ | X89: 仲手無料 | AB89: 0円 | AK89: 0 | AY89: ( 茨城 )
AY90: ( 栃木 )
B91: 仲手は 原則 振込 | E91: 売主仲手支払方法 | M91: 買主仲手支払方法 | V91: ⑥ | X91: イレギュラー | AB91: 例） 本体価格×4.5% | AK91: =ROUNDDOWN(AO70*AP91*AV91,0) -> 0 | AP91: 0.045 | AV91: 1.1 | AY91: ( 群馬 )
AY92: ( 埼玉 )
E93: 銀行振込 | M93: 銀行振込 | V93: ⑦ | X93: イレギュラー2 | AB93: 例） 100,000円 | AK93: 100000 | AV93: 1.1 | AY93: ( 千葉 )
B95: 仲手がイレギュラーの時は、⑥を選んで計算用の表に金額を手入力するか、エクセル得意なら式を入れます。あまりないと思いますが、もし売主も買主もイレギュラーだったら⑦も使いましょう。
AY96: ■三菱UFJと千葉銀行は、あっせん有にする
AY97: 三菱UFJ銀行
AY98: 千葉銀行
B99: 金 融 機 関 等 （提携ローンなら■有→） | L99: 有 | M99: 金 額 | U99: 金利 | Z99: 期間 | AE99: □ | AF99: ←中間省略の場合はチェック入れる
AE101: 売主は宅建業者？個人？ | AN101: ■ | AO101: 宅建業者 | AR101: □ | AS101: 個人・一般法人
B102: - | L102: =IFERROR(IF(MATCH($B102,$AY$97:$AY$98,0),"■"),"□") -> □ | M102: - | S102: 円 | U102: 実行時金利 | Z102: 35 | AB102: 年 | AY102: ■金融機関が変わったら、ここを変える
AE103: 売主 | AH103: =F37 -> ●登記名義人 | AY103: -
B104: - | L104: =IFERROR(IF(MATCH($B104,$AY$97:$AY$98,0),"■"),"□") -> □ | M104: - | S104: 円 | U104: - | Z104: - | AB104: 年 | AY104: 三菱UFJ銀行
AE105: 住所 | AH105: =AB37 -> ●登記名義人住所 | AY105: 三井住友銀行
B106: - | L106: =IFERROR(IF(MATCH($B106,$AY$97:$AY$98,0),"■"),"□") -> □ | M106: - | S106: 円 | U106: - | Z106: - | AB106: 年 | AY106: 三井住友ﾄﾗｽﾄﾛｰﾝ&ﾌｧｲﾅﾝｽ
AE107: ↓売主が業者なら上と同じ、売仲・中間省略は媒介業者を入れる | AY107: みずほ銀行
B108: - | L108: =IFERROR(IF(MATCH($B108,$AY$97:$AY$98,0),"■"),"□") -> □ | M108: - | S108: 円 | U108: - | Z108: - | AB108: 年 | AY108: ARUHIフラット35
AE109: 業者名 | AH109: =AH103 -> ●登記名義人 | AY109: 住信SBIネット銀行
B110: - | L110: =IFERROR(IF(MATCH($B110,$AY$97:$AY$98,0),"■"),"□") -> □ | M110: - | S110: 円 | U110: - | Z110: - | AB110: 年 | AY110: ソニー銀行
AE111: 業者住所 | AH111: =AH105 -> ●登記名義人住所 | AY111: 中央労働金庫
AY112: 千葉銀行
B113: 融資利用の有無 | O113: ■ | P113: 1. | Q113: 有 | S113: □ | T113: 2. | U113: 無 | W113: （現金） | AY113: イオン銀行
AE114: 電話 | AL114: （ | AR114: ） | AY114: auじぶん銀行
B115: 融資承認取得期日 | O115: 令和 | R115: 8 | T115: 年 | X115: 月 | AB115: 日 | AY115: 新生銀行
AE116: 免許番号 | AH116: 東京都知事 | AO116: 第 | AV116: 号
B117: 融資特約解除期日（ローン条項） | O117: 令和 | R117: 8 | T117: 年 | X117: 月 | AB117: 日
AE118: 免許年月日 | AH118: 令和 | AN118: 年 | AR118: 月 | AV118: 日
B119: 引渡・決済日 | O119: 令和 | R119: 8 | T119: 年 | X119: 月 | AB119: 日
AE120: 代表者
B121: ↓通常はないけど、手付解除期日の指定がもしあれば入れる
AE122: 宅建士
B123: 手付解除期日 | R123: - | T123: 年 | V123: - | X123: 月 | Z123: - | AB123: 日
AE124: 登録番号 | AN124: 第 | AV124: 号
AE126: 保証協会
B130: 業者情報について 保証協会は宅建協会か不動産保証協会を選べば付随する情報が自動で入ります。ただし所属は東京本部になるので、東京本部じゃない時は、重説で所属本部を変更します。 保証協会に加入していない場合は、重説の「（1）宅地建物取引業保証協会の社員」のチェックを外し「（2）供託所に営業保証金を供託」にチェックを付けます。斜線を「（1）宅地建物取引業保証協会の社員」の方に移動しておきましょう。 業務に従事する事務所が主たる事務所と違う場合は、重説で、業務に従事する事務所を手入力してください。 売主個人、買主宅建業者の場合は、業者情報の宅建士は空欄にして、重説の「供託所に関する説明」を、プルダウンで「供託所に関する説明（買主宅建業者）」に変更してください。取引態様の「媒介」「代理」「売主」のチェックは全部外しておきましょう。
B144: ■調査に使うリンク
B146: ▼ここから調べる。▼
B148: 用途地域は通常は「●●区 用途地域」で検索して市役所のHPで調べますが、
B149: 何らかの理由でHPでは調べられない時は↓を使いましょう。
B151: 都市整備局・都市計画情報（用途地域の調査 日影規制等の情報無いので参考程度。）
B152: https://www2.wagmap.jp/tokyo_tokeizu/Portal
B154: 国土交通省全国道路地図基盤等データベース(住所で検索Enter⇒公開リスト表示）
B155: https://road-basemap.mlit.go.jp/JapanRoadMapWeb/#18/35.681041/139.687214/&base=pale&ls=pale&disp=1&vs=c1g1j0h0k0l0u0t0z0r0s0m0f1&d=m
B157: 都道の調査（都道検索システム）
...

Sheet 重説
DE1: 国土交通大臣
A2: 重 要 事 項 説 明 書 | BH2: A | BJ2: 不動産の表示 | DE2: 東京都知事
DE3: 神奈川県知事
BH4: 建物の名称 | BO4: =基本入力!AB13&基本入力!AB26 | CT4: =基本入力!AH32 -> ● | CV4: 階 | CX4: =基本入力!AS13 -> ● | DA4: 号室 | DE4: 茨城県知事
DE5: 栃木県知事
BH6: 住 居 表 示 | BO6: =基本入力!F15&基本入力!J15&基本入力!N15&基本入力!X15&基本入力!AB15 -> 東京都練馬区高松3丁目 ●番●-●号 | DE6: 群馬県知事
B7: 買 主 | F7: =基本入力!F13 -> ●買主太郎 | W7: 様 | AA7: 売 主 | AE7: =VLOOKUP(基本入力!AE99,DE42:DK43,2,) -> ●登記名義人 | AV7: 様 | DE7: 埼玉県知事
DE8: 千葉県知事
BH9: 1. | BJ9: 区分所有建物
B11: 宅地建物取引業法第35条および第35条の2の規定に基づき、以下の不動産の各項目の内容について次のとおりご説明いたします。この内容は重要ですので、十分理解されるようお願いします。 本書面には、説明内容をあらかじめ印刷した事項がありますが、そのうち説明文の頭の□欄に■印をつけた記載内容が下記不動産について該当する説明です。■印のない□欄、または線で抹消した説明等は、関係ないことを示します。 | BH11: 一棟の 建物の 表示 | BM11: 所 在 | BR11: =基本入力!J24&基本入力!AB24&基本入力!AD24&基本入力!AG24&基本入力!AJ24 -> 練馬区高松3丁目 ●番地●
BM13: 構 造 | BR13: =基本入力!J28 -> 鉄筋コンクリート造陸屋根●階建
DE14: ( 東京 )
BM15: 延床面積 | BR15: =基本入力!AF28 -> ● | DE15: ( 神奈川 )
B16: 取 引 態 様 | L16: ■ | M16: 売買 | P16: ・ | Q16: □ | R16: 交換 | Z16: 取 引 態 様 | AJ16: ■ | AK16: 売買 | AN16: ・ | AO16: □ | AP16: 交換 | DE16: ( 茨城 )
BH17: 専有部分 の建物の 表示 | BM17: 家屋番号 | BR17: =基本入力!J30&基本入力!R30&基本入力!X30 -> 高松3丁目 ●番●の● | CH17: 建物の名称 | CN17: =基本入力!AF30 -> ● | DE17: ( 栃木 )
J18: ■ | K18: 媒介 | N18: ・ | O18: □ | P18: 代理 | S18: ・ | T18: □ | U18: 売主 | AH18: □ | AI18: 媒介 | AL18: ・ | AM18: □ | AN18: 代理 | AQ18: ・ | AR18: ■ | AS18: 売主 | DE18: ( 群馬 )
BM19: 種 類 | BR19: =基本入力!J32 -> 居宅 | CH19: 構 造 | CN19: =基本入力!Q32 -> ●鉄筋コンクリート造1階建 | DE19: ( 埼玉 )
B20: 宅地建物取引業者 | C20: 免許証番号 | H20: 国土交通大臣 | O20: (3) | Q20: 第 | S20: 8684 | X20: 号 | Z20: 宅地建物取引業者 | AA20: 免許証番号 | AF20: =基本入力!AH116 -> 東京都知事 | AM20: =基本入力!AM116 -> 0 | AO20: 第 | AQ20: =基本入力!AQ116 -> 0 | AV20: 号 | DE20: ( 千葉 )
BM21: 床 面 積 | BR21: =基本入力!AH32 -> ● | BV21: 階部分 | BZ21: （登記簿） | CE21: =基本入力!J34 -> 0 | CK21: ㎡ | CM21: （壁芯） | CQ21: =基本入力!AS15 -> - | CW21: ㎡
C22: 免許年月日 | H22: 令和 | L22: 6 | N22: 年 | P22: 10 | R22: 月 | T22: 2 | V22: 日 | AA22: 免許年月日 | AF22: =基本入力!AH118 -> 令和 | AJ22: =基本入力!AL118 -> 0 | AL22: 年 | AN22: =基本入力!AP118 -> 0 | AP22: 月 | AR22: =基本入力!AT118 -> 0 | AT22: 日
BM23: 建築時期 | BR23: =基本入力!U34 -> 0 | BV23: =基本入力!X34 -> 0 | BX23: 年 | BZ23: =基本入力!AB34 -> 0 | CB23: 月 | CD23: =基本入力!AF34 -> 0 | CF23: 日 | CH23: 新築
C24: 主たる 事務所の 所在地 | H24: 東京都新宿区西新宿二丁目6番1号 | AA24: 主たる 事務所の 所在地 | AF24: =VLOOKUP(基本入力!AN101,DE93:DQ94,2,) -> ●登記名義人住所
BH25: 附属建物 | BM25: （ | BN25: □ | BO25: 有 | BQ25: ・ | BR25: ■ | BS25: 無 | BU25: ） | DE25: 片岡 夏也 | DJ25: ( 東京 ) | DM25: 200499 | DQ25: ←宅建士ここに入れる
H26: 新宿住友ビル19階 | DE26: 高橋 早苗 | DJ26: ( 千葉 ) | DM26: 059758
BH27: 固定資産税等の課税対象床面積は、上記床面積とは異なり、共用部分の持分を含む面積となります。別添「●固定資産（土地・家屋）評価証明書（写し）」をご参照ください。 | DE27: 岡嶋 聖 | DJ27: ( 東京 ) | DM27: 259863
C28: 電話番号 | H28: 03 | M28: （ | N28: 3789 | S28: ） | T28: 1111 | AA28: 電話番号 | AF28: =基本入力!AH114 -> 0 | AK28: （ | AL28: =基本入力!AM114 -> 0 | AQ28: ） | AR28: =基本入力!AS114 -> 0 | DE28: 新井 拓馬 | DJ28: ( 東京 ) | DM28: 283685
C30: 商号または名称 | H30: 東京マンション株式会社 | AA30: 商号または名称 | AF30: =VLOOKUP(基本入力!AN101,DE93:DQ94,7,) -> ●登記名義人 | BH30: 上記、専有部分の壁芯面積については、別添「●東京カンテイ資料（写し）」の記載によります。以下余白
C32: 代表者氏名 | H32: 代表取締役 髙橋 正臣 | W32: ㊞ | AA32: 代表者氏名 | AF32: =基本入力!AH120:AH120 -> 0 | AU32: ㊞
B34: 説明をする宅地建物取引士 | C34: 登 録 番 号 | H34: =IF($H$36="","",VLOOKUP($H$36,$DE$25:$DM$38,6,)) -> ( 東京 ) | P34: 第 | R34: =IF($H$36="","",VLOOKUP($H$36,$DE$25:$DM$38,9,)) -> 283685 | W34: 号 | Z34: 説明をする宅地建物取引士 | AA34: 登 録 番 号 | AF34: =基本入力!AH124 -> 0 | AN34: 第 | AP34: =基本入力!AP124 -> 0 | AU34: 号
BH35: 2. | BJ35: =VLOOKUP(基本入力!R54,重説!DE47:DW48,2) -> 敷地権の目的である土地
C36: 氏 名 | H36: 新井 拓馬 | AA36: 氏 名 | AF36: =基本入力!AH122 -> 0
BH37: 符号 | BJ37: 所 在 | BV37: 地 番 | CA37: 地目（登記簿） | CG37: 地積（登記簿） | CM37: =VLOOKUP(基本入力!R54,重説!DE47:DW48,10) -> 敷地権の種類 | CS37: =VLOOKUP(基本入力!R54,重説!DE47:DW48,15) -> 敷地権の割合((準)共有持分)
C38: 業務に従事 する事務所名 | H38: =H30 -> 東京マンション株式会社 | AA38: 業務に従事 する事務所名 | AF38: =VLOOKUP(基本入力!AN101,DE93:DQ94,7,) -> ●登記名義人
BH39: 1. | BJ39: =基本入力!F42 -> 練馬区高松3丁目 | BV39: =基本入力!U42 -> ●番● | CA39: =基本入力!Y42 -> 宅地 | CG39: =基本入力!AB42 -> ● | CL39: ㎡ | CM39: =基本入力!AG42 -> 0 | CS39: =基本入力!AL42 -> 0 | CX39: 分の | CZ39: =基本入力!AT42 -> 0
C40: 業務に従事 する 事務所所在地 | H40: =H24 -> 東京都新宿区西新宿二丁目6番1号 | AA40: 業務に従事 する 事務所所在地 | AF40: =VLOOKUP(基本入力!AN101,DE93:DQ94,2,) -> ●登記名義人住所
BH41: 2. | BJ41: =基本入力!F44 -> 0 | BV41: =基本入力!U44 -> 0 | CA41: =基本入力!Y44 -> 0 | CG41: =基本入力!AB44 -> 0 | CL41: ㎡ | CM41: =基本入力!AG44 -> 0 | CS41: =基本入力!AL44 -> 0 | CX41: 分の | CZ41: =基本入力!AT44 -> 0 | DE41: 中間省略に■があったら売主を変える
H42: =H26 -> 新宿住友ビル19階 | DE42: ■ | DF42: =基本入力!AH109 -> ●登記名義人
BH43: 3. | BJ43: =基本入力!F46 -> 0 | BV43: =基本入力!U46 -> 0 | CA43: =基本入力!Y46 -> 0 | CG43: =基本入力!AB46 -> 0 | CL43: ㎡ | CM43: =基本入力!AG46 -> 0 | CS43: =基本入力!AL46 -> 0 | CX43: 分の | CZ43: =基本入力!AT46 -> 0 | DE43: □ | DF43: =基本入力!AH103 -> ●登記名義人
C44: 電話番号 | H44: =H28 -> 03 | M44: （ | N44: =N28 -> 3789 | S44: ） | T44: =T28 -> 1111 | AA44: 電話番号 | AF44: =基本入力!AH114 -> 0 | AK44: （ | AL44: =基本入力!AM114 -> 0 | AQ44: ） | AR44: =基本入力!AS114 -> 0
BH45: 4. | BJ45: =基本入力!F48 -> 0 | BV45: =基本入力!U48 -> 0 | CA45: =基本入力!Y48 -> 0 | CG45: =基本入力!AB48 -> 0 | CL45: ㎡ | CM45: =基本入力!AG48 -> 0 | CS45: =基本入力!AL48 -> 0 | CX45: 分の | CZ45: =基本入力!AT48 -> 0
B46: 供託所等に関する説明 | C46: ■ | D46: （1）宅地建物取引業保証協会の社員 | Z46: 供託所等に関する説明 | AA46: =VLOOKUP(基本入力!AN101,DE93:DQ94,12,) -> ■ | AB46: （1）宅地建物取引業保証協会の社員 | DE46: 敷地権にチェックあれば「土地」を「敷地権の目的である土地」に「権利の種類」を「敷地権の種類」にする
BH47: 5. | BJ47: =基本入力!F50 -> 0 | BV47: =基本入力!U50 -> 0 | CA47: =基本入力!Y50 -> 0 | CG47: =基本入力!AB50 -> 0 | CL47: ㎡ | CM47: =基本入力!AG50 -> 0 | CS47: =基本入力!AL50 -> 0 | CX47: 分の | CZ47: =基本入力!AT50 -> 0 | DE47: ■ | DF47: 敷地権の目的である土地 | DN47: 敷地権の種類 | DS47: 敷地権の割合((準)共有持分)
C48: 宅地建物取引業 保証協会の 名称・所在地 | J48: 公益社団法人 全国宅地建物取引業保証協会 | AA48: 宅地建物取引業 保証協会の 名称・所在地 | AH48: =基本入力!AH126 -> 0 | DE48: □ | DF48: 土地 | DN48: 権利の種類 | DS48: 権利の割合
BH49: 6. | BJ49: =基本入力!F52 -> 0 | BV49: =基本入力!U52 -> 0 | CA49: =基本入力!Y52 -> 0 | CG49: =基本入力!AB52 -> 0 | CL49: ㎡ | CM49: =基本入力!AG52 -> 0 | CS49: =基本入力!AL52 -> 0 | CX49: 分の | CZ49: =基本入力!AT52 -> 0
J50: =IF(J48="","",VLOOKUP(J48,DE56:EI57,16,)) -> 東京都千代田区岩本町2丁目6番3号 | AH50: =IFERROR(IF(AH48="","",VLOOKUP(AH48,DE56:DU58,16,)),"")
BH51: 敷地権登記 | BN51: =基本入力!R54 -> ■ | BO51: 有 | BQ51: ・ | BR51: =基本入力!V54 -> □ | BS51: 無 | BV51: 実測面積 | CA51: =基本入力!AR54 -> - | CI51: ㎡ | CK51: 合計 | CP51: =基本入力!AB54 -> 1 | CR51: 筆 | CT51: =基本入力!AG54 -> 0 | DB51: ㎡
C52: 宅地建物取引業 保証協会の 所属地方本部 名称・所在地 | J52: =IF(J48="","",VLOOKUP(J48,DE56:EI57,31,)) -> 公益社団法人 全国宅地建物取引業保証協会 東京本部 | AA52: 宅地建物取引業 保証協会の 所属地方本部 名称・所在地 | AH52: =IFERROR(IF(AH48="","",VLOOKUP(AH48,DE56:EI58,31,)),"") | DE52: 保証協会か供託所に■がついたら法務局をいれる
BH53: 借地権の場合 借地対象面積 | BV53: =基本入力!I61 -> 0 | CD53: ㎡ | CF53: ※借地契約の内容等は、別紙「借地契約書」でご説明します。 | DE53: ■ | DF53: 東京法務局 | DK53: 東京都千代田区九段南一丁目1番15号 九段第2合同庁舎
DE54: □
J55: =IF(J52="","",VLOOKUP(J52,DE60:DY74,21,)) -> 東京都有楽町1丁目9-1 日比谷サンケイビル9階 東京都宅建会館 | AH55: =IFERROR(IF($AH$52="","",VLOOKUP($AH$52,$DE$60:$DY$74,21,)),"") | BH55: 余白
DE56: 公益社団法人 全国宅地建物取引業保証協会 | DT56: 東京都千代田区岩本町2丁目6番3号 | EI56: 公益社団法人 全国宅地建物取引業保証協会 東京本部
DE57: 公益社団法人 不動産保証協会 | DT57: 東京都千代田区紀尾井町3番30号 全日会館 | EI57: 公益社団法人不動産保証協会 東京都本部
C58: 弁済業務保証金の 供託所・所在地 | J58: 東京法務局 | AA58: 弁済業務保証金の 供託所・所在地 | AH58: =VLOOKUP(AA46,DE53:DL54,2,) -> 東京法務局 | DE58: 公益社団法人 全日本不動産協会 | DT58: 東京都千代田区紀尾井町3番30号 全日会館 | EI58: 公益社団法人 全日本不動産協会 東京都本部
J60: 東京都千代田区九段南一丁目1番15号 九段第2合同庁舎 | AH60: =VLOOKUP(AA46,DE53:DL54,7,) -> 東京都千代田区九段南一丁目1番15号 九段第2合同庁舎 | BH60: 3. | BJ60: 敷地に関する権利の種類および内容 | DE60: 公益社団法人 全国宅地建物取引業保証協会 東京本部 | DY60: 東京都有楽町1丁目9-1 日比谷サンケイビル9階 東京都宅建会館
DE61: 公益社団法人 全国宅地建物取引業保証協会 神奈川本部 | DY61: 横浜市中区住吉町六丁目76番3号 神奈川県不動産会館
BH62: 敷地の面積・権利の種類 | BR62: ※「A不動産の表示」「2.土地」参照 | DE62: 公益社団法人 全国宅地建物取引業保証協会 埼玉本部 | DY62: さいたま市浦和区東高砂町六丁目15 埼玉県宅建会館
C63: □ | D63: （2）供託所に営業保証金を供託 | AA63: □ | AB63: （2）供託所に営業保証金を供託 | DE63: 公益社団法人 全国宅地建物取引業保証協会 千葉本部 | DY63: 千葉市中央区中央港一丁目17番3号 千葉県不動産会館
BH64: 借地権の場合 | BR64: 対象面積： | BX64: =基本入力!I61 -> 0 | CC64: ㎡ | CE64: （ | CF64: =基本入力!O61 -> □ | CG64: 登記簿・ | CK64: =基本入力!S61 -> □ | CL64: 実測 | CO64: ）
C65: 営業保証金の 供託所および その所在地 | AA65: 営業保証金の 供託所および その所在地 | AH65: =VLOOKUP(AA63,DE53:DL54,2,) -> 0 | DE65: 公益社団法人不動産保証協会 東京都本部 | DY65: 東京都千代田区平河町一丁目8番13号 全日東京会館
BH66: 借地権の存続期間 | BR66: =基本入力!I65 -> 0 | BU66: =基本入力!L65 -> 0 | BY66: 年 | CA66: =基本入力!R65 -> 0 | CC66: 月 | CE66: =基本入力!V65 -> 0 | CG66: 日から | CK66: =基本入力!AS65 -> 0 | CM66: 年間 | CR66: 地代 | CU66: 月額 | CX66: =基本入力!Z61 -> 0 | DB66: 円 | DE66: 公益社団法人不動産保証協会 神奈川県本部 | DY66: 神奈川県横浜市西区北幸一丁目11番15号 横浜STビル6階
AH67: =VLOOKUP(AA63,DE53:DL54,7,) -> 0 | DE67: 公益社団法人不動産保証協会 埼玉県本部 | DY67: 埼玉県さいたま市浦和区高砂三丁目10番4号 全日埼玉会館
DE68: 公益社団法人不動産保証協会 千葉県本部 | DY68: 千葉県千葉市中央区市場町4番6号 全日千葉会館
BH69: B | BJ69: 売主の表示と占有に関する事項
B70: 上記宅地建物取引士から取引士証の提示のもとに、以下の不動産の各項目について重要事項の説明を受け、説明書を受理しました。 | DE70: 公益社団法人 全日本不動産協会 東京都本部 | DY70: 東京都千代田区平河町一丁目8番13号 全日東京会館
BH71: 1. | BJ71: 売主 | BM71: （ | BN71: =VLOOKUP(基本入力!AE99,重説!DE83:DV84,3) -> ■ | BO71: 1.登記簿記載の所有者と同じ | CD71: =VLOOKUP(基本入力!AE99,重説!DE83:DV84,2) -> □ | CE71: 2.登記簿記載の所有者と異なる | CT71: ） | DE71: 公益社団法人 全日本不動産協会 神奈川県本部 | DY71: 神奈川県横浜市西区北幸一丁目11番15号 横浜STビル6階
AI72: =基本入力!F70 -> 令和 | AL72: =基本入力!I70 -> 8 | AN72: 年 | AP72: =基本入力!M70:M70 -> 0 | AR72: 月 | AT72: =基本入力!Q70:Q70 -> 0 | AV72: 日 | DE72: 公益社団法人 全日本不動産協会 埼玉県本部 | DY72: 埼玉県さいたま市浦和区高砂三丁目10番4号 全日埼玉会館
BH73: 住 所 | BL73: =VLOOKUP(基本入力!AE99,重説!DE83:DV84,10) -> ●登記名義人住所 | DE73: 公益社団法人 全日本不動産協会 千葉県本部 | DY73: 千葉県千葉市中央区市場町4番6号 全日千葉会館
B74: 買主 | Z74: =VLOOKUP(基本入力!AN101,DE89:DO90,2,) -> 0
BH75: 氏 名 | BL75: =VLOOKUP(基本入力!AE99,重説!DE83:DV84,15) -> ●登記名義人
BH77: 備 考 | BL77: =VLOOKUP(基本入力!AE99,重説!DE83:DV84,4) -> 余白 | DE77: 余白
DE78: 売主と登記名義人は同一人ですが、住所変更登記が未了となっております。売主の責任と負担で、引渡しまでに住所変更登記をしていただきます。以下余白
DE79: 本物件は、未だに登記名義人が所有しているため、本物件の所有権を移転する売主の義務については、売主が売買代金全額を受領した時に、その履行を引き受けた本物件の登記名義人である所有者が、買主にその所有権を直接移転する方法で履行することとします。以下余白
DE80: 本物件は建物の所有権移転登記が未了です。売主の責任と負担で、引渡しまでに所有権移転登記をしていただきます。以下余白
B82: 住所 | Z82: =VLOOKUP(基本入力!AN101,DE89:DO90,5,) -> 0 | BH82: 2. | BJ82: 売買契約締結時の占有に関する事項 第三者による占有 | CL82: （ | CM82: □ | CN82: 有 | CP82: ・ | CQ82: ■ | CR82: 無 | CT82: ） | DE82: ↓中間省略の場合は、チェックを付け替えて文言を入れる
DE83: ■ | DF83: ■ | DG83: □ | DH83: 本物件は、未だに登記名義人が所有しているため、本物件の所有権を移転する売主の義務については、売主が売買代金全額を受領した時に、その履行を引き受けた本物件の登記名義人である所有者が、買主にその所有権を直接移転する方法で履行することとします。以下余白 | DN83: =基本入力!AH111 -> ●登記名義人住所 | DS83: =基本入力!AH109 -> ●登記名義人
BH84: 住 所 | DE84: □ | DF84: □ | DG84: ■ | DH84: 余白 | DN84: =基本入力!AH105 -> ●登記名義人住所 | DS84: =基本入力!AH103 -> ●登記名義人
BH86: 氏 名
BH88: 占有に 関する 事項 | DE88: ↓個人売主の時は右の署名欄に自動で「売主」を入れる
DE89: ■
B90: 氏名 | Z90: =VLOOKUP(基本入力!AN101,DE89:DO90,8,) -> 0 | DE90: □ | DF90: 売主 | DI90: 住所 | DL90: 氏名 | DO90: ㊞
X91: =VLOOKUP(基本入力!AN101,DE89:DO90,11,) -> 0 | AW91: ㊞
DE92: ↓個人売主の時は宅建業者の表に住所氏名いれない、保証協会のチェック外す
DE93: ■ | DF93: =基本入力!AH111 -> ●登記名義人住所 | DK93: =基本入力!AH109 -> ●登記名義人 | DP93: ■
B94: Ⅰ | D94: 対象となる宅地または建物に直接関係する事項 | BH94: (2) | BJ94: 建築基準法に基づく制限 | CT94: （※法：建築基準法） | DE94: □ | DP94: □
B96: 1. | D96: 登記記録に記録された事項 | R96: ※所有者の所有権取得日・原因等は添付する登記事項証明書（または登記簿謄本）に記載されています。 | BH96: ①用途地域 | BI96: □ | BJ96: 1.第1種低層住居専用地域 | BY96: □ | BZ96: 6.第2種住居地域 | CN96: □ | CO96: 11.準工業地域 | DE96: ■↓抵当権、根抵当権と抵当権者、根抵当権者を連動させる
DE97: 抵当権設定 | DJ97: 抵当権者
B98: (1) | D98: 区分所有建物 | AF98: （ | AG98: 令和 | AL98: 年 | AP98: 月 | AT98: 日現在 | AW98: ） | BI98: □ | BJ98: 2.第2種低層住居専用地域 | BY98: □ | BZ98: 7.準住居地域 | CN98: □ | CO98: 12.工業地域 | DE98: 根抵当権設定 | DJ98: 根抵当権者
B100: 権利部（甲区） | C100: 所有者 | H100: 住 所 | L100: =基本入力!AH105 -> ●登記名義人住所 | BI100: □ | BJ100: 3.第1種中高層住居専用地域 | BY100: □ | BZ100: 8.田園住居地域 | CN100: □ | CO100: 13.工業専用地域
DE101: ↓敷地権じゃなければ自動で所有者入れる
H102: 氏 名 | L102: =基本入力!AH103 -> ●登記名義人 | BI102: □ | BJ102: 4.第2種中高層住居専用地域 | BY102: □ | BZ102: 9.近隣商業地域 | CN102: □ | CO102: 14.用途地域の指定なし | DE102: □
DE103: ■ | DG103: =L100 -> ●登記名義人住所 | DR103: =L102 -> ●登記名義人 | DW103: ="(持分"&基本入力!AL42&基本入力!AR42&基本入力!AT42&")" -> (持分分の)
C104: 所有権にかかる 権利に関する事項 | BI104: □ | BJ104: 5.第1種住居地域 | BY104: □ | BZ104: 10.商業地域 | CN104: □
C106: ( | D106: □ | E106: 有 | G106: ・ | H106: ■ | I106: 無 | K106: ） | BH106: ②地域・地区・街区 | BI106: □ | BJ106: 1.防火地域 | BY106: □ | BZ106: 10.風致地区 | CN106: □ | CO106: 20.臨港地区
B108: 権利部（乙区） | V108: 令和 | Z108: 年 | AC108: 月 | AF108: 日 | AI108: 第 | AM108: 号 | AN108: 債権額 金 | AV108: 万円 | BI108: □ | BJ108: 2.準防火地域 | BY108: □ | BZ108: 11.災害危険区域 | CN108: □ | CO108: 21.緑化地域
V110: =IFERROR(VLOOKUP($L$110,$DE$110:$DH$111,4,FALSE),"") | BI110: □ | BJ110: 3.新たな防火規制区域 | BY110: □ | BZ110: 12.地区計画区域 | CN110: □ | CO110: 22.生産緑地地区 | DE110: 債務者 | DH110: =基本入力!AH105&" "&基本入力!AH103 -> ●登記名義人住所 ●登記名義人
C111: 所有権以外の 権利に関する事項
L112: =IFERROR(IF(L108="","",VLOOKUP(L108,DE97:DM98,6,)),"") | BI112: □ | BJ112: 4.建築基準法第22条区域 | BY112: □ | BZ112: 13.特例容積率適用地区 | CN112: □ | CO112: 23.特定用途誘導地区
C113: ( | D113: □ | E113: 有 | G113: ・ | H113: □ | I113: 無 | K113: ）
BI114: □ | BJ114: 5.高度地区 | BO114: （ | BU114: ） | BY114: □ | BZ114: 14.特定用途制限地域 | CN114: □ | CO114: 24.特別用途地区 | DE114: ↓敷地権じゃない土地の抵当権には「登記名義人持分」をつける
DE115: 抵当権設定 | DJ115: =基本入力!AH103&"持分 "&L108 -> ●登記名義人持分
...

Sheet 借地
A2: 借 地 説 明 書
B6: 1. | D6: 貸主の表示
B8: 貸 主 | F8: 住 所 | J8: =基本入力!I63 -> 0
F10: 氏 名 | J10: =基本入力!AL63 -> 0
B12: 登記名義人と貸主が： | L12: □ | M12: 同じ | P12: ・ | Q12: □ | R12: 異なる→ | W12: 理由： | AA12: □ | AB12: 転貸借 | AF12: ・ | AG12: □ | AH12: 相続 （登記手続未了） | AQ12: ・ | AR12: □ | AS12: 5.その他参照
B15: 2. | D15: 借地の表示
B17: 所 在 地 番 | F17: （住居表示） | L17: =基本入力!F15&基本入力!J15&基本入力!N15&基本入力!X15&"号" -> 東京都練馬区高松3丁目 ●番●号 | AM17: 図 面
F19: （登記簿上の表示） | O19: =基本入力!F42&基本入力!U42 -> 練馬区高松3丁目 ●番● | AM19: □ | AN19: 有 | AP19: ・ | AQ19: ■ | AR19: 無
B21: 地 積 | F21: 登記簿 | J21: =基本入力!AG54 -> 0 | O21: ㎡ | Q21: ・ | R21: 契約 | U21: =基本入力!I61 -> 0 | Z21: ㎡ | AB21: ・ | AC21: 実測 | AF21: =基本入力!AR54 -> - | AK21: ㎡ | AM21: 地 目 | AQ21: =基本入力!Y42 -> 宅地
B24: 3. | D24: 借地契約の内容
B26: （1） 種 類 | J26: ① | L26: =基本入力!O59 -> □ | M26: 借地借家法による借地 | Y26: （ | Z26: □ | AA26: 地上権 | AE26: ・ | AF26: □ | AG26: 賃借権 | AK26: ）
L28: ア. | N28: =基本入力!AL59 -> □ | O28: 普通借地権
L30: イ. | N30: =基本入力!AR59 -> □ | O30: 定期借地権 | U30: （ | V30: □ | W30: 一般 | Z30: ・ | AA30: □ | AB30: 建物譲渡特約付 | AJ30: ・ | AK30: □ | AL30: 事業用 | AP30: ）
J32: ② | L32: =基本入力!B59 -> □ | M32: 旧借地法による借地（平成4年7月31日以前に契約されたもの）
K34: （ | L34: □ | M34: 地上権 | Q34: ・ | R34: □ | S34: 賃借権 | W34: ） | X34: （ | Y34: =基本入力!AF61 -> 0 | AN34: ）
B36: （2） 期 間 | J36: =基本入力!I65 -> 0 | M36: =基本入力!L65 -> 0 | Q36: 年 | S36: =基本入力!R65 -> 0 | U36: 月 | W36: =基本入力!V65 -> 0 | Y36: 日 | AA36: ～ | AC36: =基本入力!AA65 -> 0 | AF36: =基本入力!AD65 -> 0 | AJ36: 年 | AL36: =基本入力!AJ65 -> 0 | AN36: 月 | AP36: =基本入力!AN65 -> 0 | AR36: 日 | AT36: まで | AZ36: =基本入力!I65 -> 0 | BC36: =基本入力!L65 -> 0 | BG36: 年 | BI36: =基本入力!R65 -> 0 | BK36: 月 | BM36: =基本入力!V65 -> 0 | BO36: 日から | BS36: =基本入力!AS65 -> 0 | BU36: 年間
B38: （3） 地 代 | J38: 月額 | M38: =基本入力!Z61 -> 0 | T38: 円 | V38: （区分所有建物の場合、区分所有者の負担額）
B40: （4） 更新の可否 | J40: 更新料の有無 | Q40: （ | R40: □ | S40: 有 | U40: ・ | V40: □ | W40: 無 | Y40: ） | Z40: 更新料の額： | AN40: 円
C42: ■ | D42: 可 | F42: ・ | G42: □ | H42: 否 | K42: ※借地借家法による普通借地権・旧借地法による借地権の場合は、更新することができます。ただし、土地所有者（貸主）の更新拒絶に正当事由があるときは更新できません。
K45: ※定期借地権の場合は、更新できません。
B47: （5） 登記の状況 | J47: 借地権の登記 | Q47: （ | R47: □ | S47: 有 | U47: ・ | V47: □ | W47: 無 | Y47: ） | Z47: ・ | AA47: 建物の登記 | AG47: （ | AH47: ■ | AI47: 有 | AK47: ・ | AL47: □ | AM47: 無 | AO47: ）
K49: ※借地権は、その登記がなくても土地の上に借地権者が登記されている建物を所有するときは、これをもって第三者に対抗することができます（借地借家法第10条、建物保護に関する法律第1条）。
B52: （6） その他の 契約内容 | J52: ① | L52: 私道負担の有無 | T52: （ | U52: □ | V52: 有 | X52: ・ | Y52: ■ | Z52: 無 | AB52: ）
J54: ② | L54: 第三者に借地権譲渡・転貸のときの土地所有者（貸主）の承諾
L56: （ | M56: □ | N56: 要する | R56: ・ | S56: □ | T56: 書面通知で可 | AA56: ・ | AB56: □ | AC56: 不要 | AF56: ）
L58: 承諾料の有無 | S58: （ | T58: □ | U58: 有 | W58: ・ | X58: □ | Y58: 無 | AA58: ） | AB58: 承諾料の額： | AO58: 円
J60: ③ | L60: 増・改築のときの土地所有者（貸主）の承諾
L62: （ | M62: □ | N62: 要する | R62: ・ | S62: □ | T62: 書面通知で可 | AA62: ・ | AB62: □ | AC62: 不要 | AF62: ）
L64: 承諾料の有無 | S64: （ | T64: □ | U64: 有 | W64: ・ | X64: □ | Y64: 無 | AA64: ） | AB64: 承諾料の額： | AO64: 円
J66: ④ | L66: 契約書が公正証書化されて | Z66: （ | AA66: □ | AB66: いる | AE66: ・ | AF66: ■ | AG66: いない | AK66: ）
J68: ⑤ | L68: 地代改定に関する特約 | V68: （ | W68: □ | X68: 無 | Z68: ・ | AA68: □ | AB68: 有 | AD68: →内容： | AW68: ）
J70: ⑥ | L70: [一般定期借地権・事業用借地権の場合]
L72: 契約終了時における建物の取壊しに関する特約 | AH72: （ | AI72: □ | AJ72: 有 | AL72: ・ | AM72: ■ | AN72: 無 | AP72: ）
B75: 4. | D75: 対象不動産の借地権の譲渡
B77: 借地権譲渡についての 土地所有者（貸主）の承諾 | O77: □ | P77: 取得済→別添「承諾書」参照 | AD77: ・ | AE77: □ | AF77: 未取得（承諾料の負担者は売主です）
O79: □ | P79: 書面通知で可 | W79: ・ | X79: □ | Y79: 不要
B82: 5. | D82: その他
B84: 余白 | AY84: 更新料については、土地賃貸契約書に明記された事項がないため、詳細は不明です。以下余白
AY89: ←その他が足りなかったら、ドラッグして伸ばして2ページにしよう。

Sheet 売契（業者）
B1: 売主宅建業者用 | AN1: 収入印紙
A2: 不 動 産 売 買 契 約 書 | BH2: 建物の構造耐力上主要な部分等の状況について確認した事項（第19条） | CJ2: （ | CK2: 既存の住宅に | CQ2: ■ | CR2: 該当する・ | CW2: □ | CX2: 該当しない | DC2: ）
BH4: 「建物の構造耐力上主要な部分」または「雨水の浸入を防止する部分」の状況について建物状況調査により売主、買主の双方が確認した事項 | CV4: □ | CW4: 1. | CX4: 有 | CZ4: ■ | DA4: 2. | DB4: 無
B7: A | D7: 不動産の表示 | BH7: 確認事項を記載した資料の名称
B9: 一棟の建物の表示 | BH9: 資料作成者 | CF9: 資料作成年月日
B11: 所 在 | I11: =基本入力!J24&基本入力!AB24&基本入力!AD24&基本入力!AG24&基本入力!AJ24 -> 練馬区高松3丁目 ●番地●
B13: 建物の名称 | I13: =基本入力!AB13&基本入力!AB26
B15: 構 造 | I15: =基本入力!J28 -> 鉄筋コンクリート造陸屋根●階建 | AJ15: 延床面積 | AO15: =基本入力!AF28 -> ● | AV15: ㎡ | BH15: 特 約
DF16: ■電子契約
B17: 専有部分の建物の表示 | BH17: 1 | BJ17: 本物件に関わる管理費・修繕積立金等について滞納分がある場合は、本物件引渡し時までに売主の責任と負担において清算するものとします。以下余白 | DF17: 本契約の成立を証するため、本書の電磁的記録を作成し、売主および買主が合意の後電子署名を施し、各自その電磁的記録を保管する。そのため第20条における印紙は貼付しないものとする。
B19: 家屋番号 | G19: =基本入力!J30&基本入力!R30&基本入力!X30 -> 高松3丁目 ●番●の● | U19: 建物の名称 | AA19: =基本入力!AF30 -> ● | AL19: 種 類 | AQ19: =基本入力!J32 -> 居宅
B21: 構 造 | G21: =基本入力!Q32 -> ●鉄筋コンクリート造1階建 | Y21: 床 面 積 | AD21: =基本入力!AH32 -> ● | AG21: 階部分 | AL21: （登記簿） | AQ21: =基本入力!J34 -> 0 | AV21: ㎡
B23: 附属建物 | G23: （ | H23: =重説!BN25 -> □ | I23: 有 | K23: ・ | L23: =重説!BR25 -> ■ | M23: 無 | O23: ） | P23: =重説!BV25 -> 0
B25: =VLOOKUP(基本入力!R54,'売契（業者）'!DF26:DZ28,2) -> 敷地権の目的である土地の表示 | DF25: 敷地権にチェックあれば「土地」を「敷地権の目的である土地」に「権利の種類」を「敷地権の種類」にする
DF26: ■ | DG26: 敷地権の目的である土地の表示 | DO26: 敷地権の種類 | DT26: 敷地権の割合 ((準)共有持分) | DY26: 敷地権の種類が借地権（地上権、賃借権）の場合
B27: 符号 | D27: 所 在 | P27: 地 番 | U27: 地目（登記簿） | AA27: 地積（登記簿） | AG27: =VLOOKUP(基本入力!R54,'売契（業者）'!DF26:DZ28,10) -> 敷地権の種類 | AM27: =VLOOKUP(基本入力!R54,'売契（業者）'!DF26:DZ28,15) -> 敷地権の割合 ((準)共有持分) | DF27: □ | DG27: 土地の表示 | DO27: 権利の種類 | DT27: 権利の割合 ((準)共有持分) | DY27: 権利の種類が借地権（地上権、賃借権）の場合
B29: 1. | D29: =基本入力!F42 -> 練馬区高松3丁目 | P29: =基本入力!U42 -> ●番● | U29: =基本入力!Y42 -> 宅地 | AA29: =基本入力!AB42 -> ● | AF29: ㎡ | AG29: =基本入力!AG42 -> 0 | AM29: =基本入力!AL42 -> 0 | AR29: 分の | AT29: =基本入力!AT42 -> 0
B31: 2. | D31: =基本入力!F44 -> 0 | P31: =基本入力!U44 -> 0 | U31: =基本入力!Y44 -> 0 | AA31: =基本入力!AB44 -> 0 | AF31: ㎡ | AG31: =基本入力!AG44 -> 0 | AM31: =基本入力!AL44 -> 0 | AR31: 分の | AT31: =基本入力!AT44 -> 0
B33: 3. | D33: =基本入力!F46 -> 0 | P33: =基本入力!U46 -> 0 | U33: =基本入力!Y46 -> 0 | AA33: =基本入力!AB46 -> 0 | AF33: ㎡ | AG33: =基本入力!AG46 -> 0 | AM33: =基本入力!AL46 -> 0 | AR33: 分の | AT33: =基本入力!AT46 -> 0
B35: 4. | D35: =基本入力!F48 -> 0 | P35: =基本入力!U48 -> 0 | U35: =基本入力!Y48 -> 0 | AA35: =基本入力!AB48 -> 0 | AF35: ㎡ | AG35: =基本入力!AG48 -> 0 | AM35: =基本入力!AL48 -> 0 | AR35: 分の | AT35: =基本入力!AT48 -> 0
B37: 5. | D37: =基本入力!F50 -> 0 | P37: =基本入力!U50 -> 0 | U37: =基本入力!Y50 -> 0 | AA37: =基本入力!AB50 -> 0 | AF37: ㎡ | AG37: =基本入力!AG50 -> 0 | AM37: =基本入力!AL50 -> 0 | AR37: 分の | AT37: =基本入力!AT50 -> 0
B39: 6. | D39: =基本入力!F52 -> 0 | P39: =基本入力!U52 -> 0 | U39: =基本入力!Y52 -> 0 | AA39: =基本入力!AB52 -> 0 | AF39: ㎡ | AG39: =基本入力!AG52 -> 0 | AM39: =基本入力!AL52 -> 0 | AR39: 分の | AT39: =基本入力!AT52 -> 0
B41: 敷地権登記 | H41: =基本入力!R54 -> ■ | I41: 有 | K41: ・ | L41: =基本入力!V54 -> □ | M41: 無 | P41: 実測面積 | U41: =基本入力!AR54 -> - | AC41: ㎡ | AE41: 合計 | AJ41: =基本入力!AB54 -> 1 | AL41: 筆 | AN41: =基本入力!AG54 -> 0 | AV41: ㎡
B43: =VLOOKUP(基本入力!R54,'売契（業者）'!DF26:DZ28,20) -> 敷地権の種類が借地権（地上権、賃借権）の場合 | H43: 土地所有者 | N43: 住所 | Q43: =IFERROR(基本入力!I63,"") -> 0
N45: 氏名 | Q45: =IFERROR(基本入力!AL63,"") -> 0
H47: 目的 | K47: =基本入力!AF61 -> 0 | AA47: 期限 | AD47: =IFERROR(基本入力!AA65,"") -> 0 | AG47: =IFERROR(基本入力!AD65,"") -> 0 | AK47: 年 | AM47: =IFERROR(基本入力!AJ65,"") -> 0 | AO47: 月 | AQ47: =IFERROR(基本入力!AN65,"") -> 0 | AS47: 日まで
BH48: 売主 | BK48: =VLOOKUP(基本入力!AE99,DF48:DK50,2,) -> ●登記名義人 | CD48: と買主 | CH48: =基本入力!F13 -> ●買主太郎 | DA48: とは | DF48: 中間省略に■があったら売主を変える
H49: 種類 | K49: =IFERROR(基本入力!B59,"") -> □ | L49: 1. | M49: 旧法による借地権 | U49: =IFERROR(基本入力!AL59,"") -> □ | V49: 2. | W49: 普通借地権 | AC49: =IFERROR(基本入力!AR59,"") -> □ | AD49: 3. | AE49: 定期借地権 | AK49: 地代 | AN49: 月額 | AQ49: =IFERROR(基本入力!Z61,"") -> 0 | AV49: 円 | DF49: ■ | DG49: =基本入力!AH109 -> ●登記名義人
BH50: =IF(基本入力!AB18="","",VLOOKUP(基本入力!AB18,DF52:DJ54,5,)) -> 表記記載の区分所有建物（以下「本物件」という。）の売買契約を締結した。その証として本契約書を壱通作成し、売主・買主署（記）名押印のうえ、買主が原本を、売主がその写しを保有する。 | DF50: □ | DG50: =基本入力!AH103 -> ●登記名義人
B51: 特記事項 | D51: 余白
DF52: 一通作成 | DJ52: 表記記載の区分所有建物（以下「本物件」という。）の売買契約を締結した。その証として本契約書を壱通作成し、売主・買主署（記）名押印のうえ、買主が原本を、売主がその写しを保有する。
DF53: 二通作成 | DJ53: 表記記載の区分所有建物（以下「本物件」という。）の売買契約を締結した。その証として本契約書を弐通作成し、売主・買主署（記）名押印のうえ、各その壱通を保有する。
DF54: 電子契約 | DJ54: 表記記載の区分所有建物（以下「本物件」という。）の売買契約を締結した。その証として売主と買主は、本書の電磁的記録を作成し、売主及び買主が合意の後電子署名を施し、各自その電磁的記録を保管する。
CO55: =基本入力!F70 -> 令和 | CR55: =基本入力!I70 -> 8 | CT55: 年 | CV55: =基本入力!M70 -> 0 | CX55: 月 | CZ55: =基本入力!Q70 -> 0 | DB55: 日
B58: B | D58: 売買代金および支払い方法等 | BH58: 売主 | BL58: 免許証番号 | BV58: =基本入力!AH116 -> 東京都知事 | CB58: =基本入力!AM116 -> 0 | CD58: 第 | CF58: =基本入力!AQ116 -> 0 | CK58: 号
B60: 売 買 代 金 （第1条） | AE60: 金 | AG60: =基本入力!AA70 -> 0 | AV60: 円 | BL60: 事務所の所在地 | BV60: =基本入力!AH111 -> ●登記名義人住所
B62: （上記売買代金のうち消費税額および地方消費税額の合計額） | AE62: 金 | AG62: =基本入力!AA74 -> 0 | AV62: 円 | BL62: 商号または名称 | BV62: =基本入力!AH109 -> ●登記名義人
B64: 手付金 （第2条） | P64: 本契約締結時支払い | AE64: 金 | AG64: =基本入力!AA72 -> 0 | AV64: 円 | BL64: 代表者氏名 | BV64: =基本入力!AH120 -> 0
CW65: ㊞
B66: 内 金 （第3条） | K66: 第1回 | U66: 年 | Y66: 月 | AC66: 日 | AE66: 金 | AV66: 円 | BL66: 登 録 番 号 | BV66: =基本入力!AH124 -> 0 | CB66: 第 | CD66: =基本入力!AP124 -> 0 | CK66: 号
K68: 第2回 | U68: 年 | Y68: 月 | AC68: 日 | AE68: 金 | AV68: 円 | BL68: 宅地建物取引士氏名 | BV68: =基本入力!AH122 -> 0
CW69: ㊞
B70: 残代金 （第3条） | P70: =基本入力!O119 -> 令和 | S70: =基本入力!R119 -> 8 | U70: 年 | W70: =基本入力!V119 -> 0 | Y70: 月 | AA70: =基本入力!Z119 -> 0 | AC70: 日 | AE70: 金 | AG70: =AG60-AG64-AG66-AG68 -> 0 | AV70: 円
B72: 引渡日 （第6条） | P72: ■ | Q72: 1. | R72: 売買代金全額受領日 | AC72: □ | AD72: 2.
BH73: 買主 | BL73: 住所
B74: 手付解除期日 （第14条第1項） | P74: =基本入力!O123 -> 0 | S74: =基本入力!R123 -> - | U74: 年 | W74: =基本入力!V123 -> - | Y74: 月 | AA74: =基本入力!Z123 -> - | AC74: 日
B76: 違約金の額 （第15条第2項） | P76: □ | Q76: 1.手付金の額 | X76: ■ | Y76: 2.売買代金の | AF76: =重説!CC492 -> 10 | AH76: ％相当額 | AM76: □ | AN76: 3. | AV76: 円
BL77: 氏名
B78: 融 資 | D78: 融資利用の有無 （第17条） | Q78: =基本入力!O113 -> ■ | R78: 1. | S78: 有 | U78: =基本入力!S113 -> □ | V78: 2. | W78: 無 | CG78: ㊞
D80: 申込先： | I80: =基本入力!B102 -> - | AE80: 融資金額 金 | AL80: =基本入力!M102 -> - | AV80: 円 | BH80: 仲介（媒介）人 | CC80: （この契約書は宅地建物取引業法第37条に定められている書面を兼ねています）
D82: 申込先： | I82: =基本入力!B104 -> - | AE82: 融資金額 金 | AL82: =基本入力!M104 -> - | AV82: 円
BH83: 免許証番号 | BO83: =重説!H20 -> 国土交通大臣 | BU83: =重説!O20 -> (3) | BW83: 第 | BY83: =重説!S20 -> 8684 | CD83: 号
D84: 申込先： | I84: =基本入力!B106 -> - | AE84: 融資金額 金 | AL84: =基本入力!M106 -> - | AV84: 円
BH85: 事務所所在地 | BO85: =重説!H24 -> 東京都新宿区西新宿二丁目6番1号
D86: 申込先： | I86: =基本入力!B108 -> - | AE86: 融資金額 金 | AL86: =基本入力!M108 -> - | AV86: 円
BO87: =重説!H26 -> 新宿住友ビル19階
D88: 申込先： | I88: =基本入力!B110 -> - | AE88: 融資金額 金 | AL88: =基本入力!M110 -> - | AV88: 円
BH89: 商 号 | BO89: =重説!H30 -> 東京マンション株式会社
D90: 融資承認取得期日 （同条第2項） | AE90: =基本入力!O115 -> 令和 | AH90: =基本入力!R115 -> 8 | AJ90: 年 | AL90: =基本入力!V115 -> 0 | AN90: 月 | AP90: =基本入力!Z115 -> 0 | AR90: 日
BH91: 代 表 者 等 | BO91: =重説!H32 -> 代表取締役 髙橋 正臣 | CD91: ㊞
D92: 融資利用の特約に基づく契約解除期日 （同条第2項） | AE92: =基本入力!O117 -> 令和 | AH92: =基本入力!R117 -> 8 | AJ92: 年 | AL92: =基本入力!V117 -> 0 | AN92: 月 | AP92: =基本入力!Z117 -> 0 | AR92: 日
BH93: 登録番号 | BO93: =重説!H34 -> ( 東京 ) | BU93: 第 | BW93: =重説!R34 -> 283685 | CB93: 号
B95: 賃借権譲渡承諾の特約に基づく契約解除期日 （第18条第2項） | AE95: =重説!CN467 -> 0 | AH95: =重説!CQ467 -> - | AJ95: 年 | AL95: =重説!CU467 -> - | AN95: 月 | AP95: =重説!CY467 -> - | AR95: 日 | BH95: 宅地建物取引士 | BS95: =重説!H36 -> 新井 拓馬
B99: （売買の目的物および売買代金） | BH99: （修補の遅滞等を含む契約違反による解除・違約金）
B100: 第1条 | E100: 売主は、買主に対し、表記区分所有建物（以下「建物」といいます。）および表記敷地権の目的である土地の（準）共有持分（以下「土地」といい、建物および土地を総称して「本物件」といいます。）を表記売買代金（以下「売買代金」といいます。）で売渡し、買主は、これを買受けました。 | BH100: 第15条 | BK100: 売主、買主は、その相手方が本契約にかかる債務の履行を遅滞したとき、その相手方に対し、相当の期間を定めて債務の履行を催告したうえで、その期間内に履行がないときは、本契約を解除することができます。なお、第12条第1項の契約不適合について売主が同条同項第1号の修補または同項第2号の代金減額を遅滞した場合を含めます。
B104: （手付金） | BK104: 2 前項の規定による契約解除において、売主、買主は、その相手方に表記違約金（以下「違約金」といいます。）の支払いを請求することができます。ただし、本契約および社会通念に照らして相手方の責めに帰すことができない事由によるものであるときは、違約金の請求はできません。なお、違約金に関し、現に生じた損害額の多寡を問わず、相手方に違約金の増減を請求することができません。
B105: 第2条 | E105: 買主は、売主に対し、表記手付金（以下「手付金」といいます。）を本契約締結と同時に支払います。
E106: 2 前項の手付金は、表記残代金（以下「残代金」といいます。）支払いのときに、売買代金の一部に無利息にて充当します。
B108: （売買代金の支払いの時期、方法等）
B109: 第3条 | E109: 買主は、売主に対し、売買代金として、表記内金（以下「内金」といいます。）、残代金を、表記各支払日までに現金または預金小切手をもって支払います。 | BK109: 3 違約金の支払い、清算は次のとおり行います。
BK110: （1）売主が違約した場合、売主は、買主に対し、すみやかに受領済みの金員を無利息にて返還するとともに、違約金を支払います。 （2）買主が違約した場合、違約金が支払い済みの金員を上回るときは、買主は、売主に対し、すみやかにその差額を支払い、支払い済みの金員が違約金を上回るときは、売主は、買主に対し、受領済みの金員から違約金相当額を控除して、すみやかに残額を無利息にて返還します。
B112: （売買対象面積）
B113: 第4条 | E113: 売主、買主は、本物件の売買対象面積は、土地については表記土地面積と、建物については表記建物面積とし、同面積が測量等による面積と差異が生じた場合であっても、互いに異議を申し出ず、売買代金の変更、本契約の解除、損害賠償の請求その他何らの請求もしないものとします。
B117: （所有権等の移転の時期） | BH117: （反社会的勢力の排除）
B118: 第5条 | E118: 本物件の所有権（敷地権の種類が借地権のときは、建物の所有権と土地に関する借地権。以下「所有権等」といいます。）は、買主が売主に対して売買代金全額を支払い、売主がこれを受領した時に売主から買主に移転します。 | BH118: 第16条 | BK118: 売主、買主は、その相手方に対し、次の各号の事項を確約します。 （1）自らが、暴力団、暴力団関係企業、総会屋もしくはこれらに準ずる者またはその構成員（以下総称して「反社会的勢力」といいます。）ではないこと。 （2）自らの役員（業務を執行する社員、取締役、執行役またはこれらに準ずる者をいいます。）が反社会的勢力ではないこと。 （3）反社会的勢力に自己の名義を利用させ、本契約を締結するものでないこと。 （4）本物件の引渡しおよび売買代金全額の支払いのいずれもが終了するまでの間に、自らまたは第三者を利用して、本契約に関して次の行為をしないこと。 ア 相手方に対する脅迫的な言動または暴力を用いる行為 イ 偽計または威力を用いて相手方の業務を妨害し、または信用を毀損する行為
B121: （引渡し）
B122: 第6条 | E122: 売主は、買主に対し、本物件を表記引渡日までに引渡します。
B125: （抵当権等の抹消）
B126: 第7条 | E126: 売主は、買主に対し、本物件について、第5条の所有権等の移転時期までにその責任と負担において、先取特権、抵当権等の担保権、地上権、賃借権等の用益権その他名目形式の如何を問わず、買主の完全な所有権等の行使を阻害する一切の負担を除去抹消します。
BK129: 2 売主、買主の一方について、次のいずれかに該当した場合には、その相手方は、何らの催告を要せずして、本契約を解除することができます。 ア 前項（1）または（2）の確約に反する申告をしたことが判明した場合 イ 前項（3）の確約に反し契約をしたことが判明した場合 ウ 前項（4）の確約に反した行為をした場合
B130: （所有権等の移転登記等）
B131: 第8条 | E131: 売主は、買主に対し、売買代金全額の受領と同時に本物件について、買主の名義に、所有権等の移転登記申請手続をします。
E134: 2 前項の登記申請に要する費用は、買主の負担とします。ただし、本物件に関し、前項の所有権等移転登記申請手続前の所有権等登記名義人の住所、氏名等の変更登記を要する場合の費用は、売主の負担とします。
BK135: 3 買主は、売主に対し、自らまたは第三者をして本物件を反社会的勢力の事務所その他の活動の拠点に供しないことを確約します。 4 売主は、買主が前項に反した行為をした場合には、何らの催告を要せずして、本契約を解除することができます。 5 第2項または前項の規定により本契約が解除された場合には、解除された者は、その相手方に対し、違約金（損害賠償額の予定）として売買代金の20％相当額を支払います。 6 第2項または第4項の規定により本契約が解除された場合には、解除された者は、解除により生じる損害について、その相手方に対し一切の請求をすることができません。 7 第2項および第4項の規定による解除については第15条第1項を適用せず、第5項の違約金および前項の規定については第15条第2項を適用しません。
B137: （引渡し完了前の滅失・損傷）
B138: 第9条 | E138: 売主、買主は、本物件の引渡し完了前に天災地変、その他売主、買主いずれの責めにも帰すことのできない事由により、本物件が滅失または損傷して、修補が不能、または修補に過大な費用を要し、本契約の履行が不可能となったとき、互いに書面により通知して、本契約を解除することができます。また、買主は、本契約が解除されるまでの間、売買代金の支払いを拒むことができます。 2 本物件の引渡し完了前に、前項の事由によって本物件が損傷した場合であっても、修補することにより本契約の履行が可能であるときは、売主は、本物件を修補して買主に引渡します。 3 第1項の規定により本契約が解除されたとき、売主は、買主に対し、受領済みの金員を無利息にてすみやかに返還します。
BH145: （融資利用の特約）
BH146: 第17条 | BK146: 買主は、売買代金に関して、表記融資金を利用するとき、本契約締結後すみやかにその融資の申込み手続をします。
B148: （物件状況等報告書） | BK148: 2 表記融資承認取得期日までに、前項の融資の全部または一部の金額につき承認が得られないとき、または否認されたとき、買主は、売主に対し、表記契約解除期日までであれば、本契約を解除することができます。
B149: 第10条 | E149: 売主は、買主に対し、本物件について、本契約締結時における状況等を別紙「物件状況等報告書（告知書）」に記載して説明します。
BK151: 3 前項により本契約が解除されたとき、売主は、買主に対し、受領済みの金員を無利息にてすみやかに返還します。
B152: （公租公課等の分担） | BK152: 4 買主が第1項の規定による融資の申込み手続を行わず、または故意に融資の承認を妨げた場合は、第2項の規定による解除はできません。
B153: 第11条 | E153: 売主、買主は、本物件から生ずる収益または本物件に対して賦課される固定資産税、都市計画税等の公租公課ならびに管理費および修繕積立金等、ガス、水道、電気料金および各種負担金等の諸負担について、引渡完了日の前日までの分を売主の収益または負担とし、引渡完了日以降の分を買主の収益または負担として、引渡完了日において清算します。なお、公租公課の起算日は1月1日とし、売主に管理費および修繕積立金等の滞納があった場合にはその額を売買代金額から控除の上、買主においてこれを支払うこととします。
BH155: （敷地権が賃借権の場合の特約）
BH156: 第18条 | BK156: 売主は、敷地権の種類が賃借権のとき、当該賃借権を買主に譲渡することについて、土地所有者の賃借権譲渡承諾書を取得します。なお、承諾料は売主の負担とします。
B159: （契約不適合による修補請求、代金減額請求および損害賠償請求） | BK159: 2 前項の賃借権譲渡承諾書を交付できないとき、売主は、買主に対し、本契約を表記賃借権譲渡承諾の特約に基づく契約解除期日までであれば、書面による通知により解除することができます。
B160: 第12条 | E160: 売主は、買主に対し、引渡された本物件が種類または品質に関して契約の内容に適合しないもの（以下「契約不適合」といいます。）であるときは、責任を負うものとし、買主は、売主に対し、次のとおり請求することができます。
BK162: 3 前項により本契約を解除したとき、売主は、買主に対し、受領済みの金員を無利息にてすみやかに返還します。
E163: （1）買主は、売主に対し、本物件の修補を請求することができます。ただし、売主は、買主に不相当な負担を課すものではないときは、買主が請求した方法と異なる方法による修補をすることができます。 （2）前号の場合において、買主が、売主に対し、相当の期間を定めて修補の催告をし、その期間内に修補をしないときは、買主はその不適合の程度に応じて代金の減額を請求することができます。ただし、買主が売主に催告しても修補を受ける見込みがないことが明らかであるときは、催告をすることなく直ちに代金の減額を請求することができます。 （3）引渡された本物件に契約不適合があるときは、その契約不適合がこの契約及び取引上の社会通念に照らして軽微であるときを除き、買主は、売主に対し、相当の期間を定めて本物件の修補を催告したうえ、この契約を解除することができます。 （4）第1項の契約不適合が買主の責めに帰すべき事由によるものであるときは、買主は、第1号の修補請求、第2号の代金減額請求、第3号の契約解除、いずれもすることはできません。
BH164: （建物の構造耐力上主要な部分等の状況について双方が確認した事項）
...

Sheet 売契（一般法人）
B1: 消費者契約用 | AN1: 収入印紙
A2: 不 動 産 売 買 契 約 書 | BH2: 建物の構造耐力上主要な部分等の状況について確認した事項（第19条） | CJ2: （ | CK2: 既存の住宅に | CQ2: ■ | CR2: 該当する・ | CW2: □ | CX2: 該当しない | DC2: ）
BH4: 「建物の構造耐力上主要な部分」または「雨水の浸入を防止する部分」の状況について建物状況調査により売主、買主の双方が確認した事項 | CV4: □ | CW4: 1. | CX4: 有 | CZ4: ■ | DA4: 2. | DB4: 無
B7: A | D7: 不動産の表示 | BH7: 確認事項を記載した資料の名称
B9: 一棟の建物の表示 | BH9: 資料作成者 | CF9: 資料作成年月日
B11: 所 在 | I11: =基本入力!J24&基本入力!AB24&基本入力!AD24&基本入力!AG24&基本入力!AJ24 -> 練馬区高松3丁目 ●番地●
B13: 建物の名称 | I13: =基本入力!AB13&基本入力!AB26
B15: 構 造 | I15: =基本入力!J28 -> 鉄筋コンクリート造陸屋根●階建 | AJ15: 延床面積 | AO15: =基本入力!AF28 -> ● | AV15: ㎡ | BH15: 特 約
B17: 専有部分の建物の表示 | BH17: 1 | BJ17: 本物件に関わる管理費・修繕積立金等について滞納分がある場合は、本物件引渡し時までに売主の責任と負担において清算するものとします。以下余白
B19: 家屋番号 | G19: =基本入力!J30&基本入力!R30&基本入力!X30 -> 高松3丁目 ●番●の● | U19: 建物の名称 | AA19: =基本入力!AF30 -> ● | AL19: 種 類 | AQ19: =基本入力!J32 -> 居宅
BJ20: 本契約の成立を証するため、本書の電磁的記録を作成し、売主および買主が合意の後電子署名を施し、各自その電磁的記録を保管する。そのため第20条における印紙は貼付しないものとする。
B21: 構 造 | G21: =基本入力!Q32 -> ●鉄筋コンクリート造1階建 | Y21: 床 面 積 | AD21: =基本入力!AH32 -> ● | AG21: 階部分 | AL21: （登記簿） | AQ21: =基本入力!J34 -> 0 | AV21: ㎡
B23: 附属建物 | G23: （ | H23: =重説!BN25 -> □ | I23: 有 | K23: ・ | L23: =重説!BR25 -> ■ | M23: 無 | O23: ） | P23: =重説!BV25 -> 0
B25: =VLOOKUP(基本入力!R54,'売契（一般法人）'!DF26:DZ28,2) -> 敷地権の目的である土地の表示
DF26: 敷地権にチェックあれば「土地」を「敷地権の目的である土地」に「権利の種類」を「敷地権の種類」にする
B27: 符号 | D27: 所 在 | P27: 地 番 | U27: 地目（登記簿） | AA27: 地積（登記簿） | AG27: =VLOOKUP(基本入力!R54,'売契（一般法人）'!DF26:DZ28,10) -> 敷地権の種類 | AM27: =VLOOKUP(基本入力!R54,'売契（一般法人）'!DF26:DZ28,15) -> 敷地権の割合 ((準)共有持分) | DF27: ■ | DG27: 敷地権の目的である土地の表示 | DO27: 敷地権の種類 | DT27: 敷地権の割合 ((準)共有持分) | DY27: 敷地権の種類が借地権（地上権、賃借権）の場合
DF28: □ | DG28: 土地の表示 | DO28: 権利の種類 | DT28: 権利の割合 ((準)共有持分) | DY28: 権利の種類が借地権（地上権、賃借権）の場合
B29: 1. | D29: =基本入力!F42 -> 練馬区高松3丁目 | P29: =基本入力!U42 -> ●番● | U29: =基本入力!Y42 -> 宅地 | AA29: =基本入力!AB42 -> ● | AF29: ㎡ | AG29: =基本入力!AG42 -> 0 | AM29: =基本入力!AL42 -> 0 | AR29: 分の | AT29: =基本入力!AT42 -> 0
B31: 2. | D31: =基本入力!F44 -> 0 | P31: =基本入力!U44 -> 0 | U31: =基本入力!Y44 -> 0 | AA31: =基本入力!AB44 -> 0 | AF31: ㎡ | AG31: =基本入力!AG44 -> 0 | AM31: =基本入力!AL44 -> 0 | AR31: 分の | AT31: =基本入力!AT44 -> 0
B33: 3. | D33: =基本入力!F46 -> 0 | P33: =基本入力!U46 -> 0 | U33: =基本入力!Y46 -> 0 | AA33: =基本入力!AB46 -> 0 | AF33: ㎡ | AG33: =基本入力!AG46 -> 0 | AM33: =基本入力!AL46 -> 0 | AR33: 分の | AT33: =基本入力!AT46 -> 0
B35: 4. | D35: =基本入力!F48 -> 0 | P35: =基本入力!U48 -> 0 | U35: =基本入力!Y48 -> 0 | AA35: =基本入力!AB48 -> 0 | AF35: ㎡ | AG35: =基本入力!AG48 -> 0 | AM35: =基本入力!AL48 -> 0 | AR35: 分の | AT35: =基本入力!AT48 -> 0
B37: 5. | D37: =基本入力!F50 -> 0 | P37: =基本入力!U50 -> 0 | U37: =基本入力!Y50 -> 0 | AA37: =基本入力!AB50 -> 0 | AF37: ㎡ | AG37: =基本入力!AG50 -> 0 | AM37: =基本入力!AL50 -> 0 | AR37: 分の | AT37: =基本入力!AT50 -> 0
B39: 6. | D39: =基本入力!F52 -> 0 | P39: =基本入力!U52 -> 0 | U39: =基本入力!Y52 -> 0 | AA39: =基本入力!AB52 -> 0 | AF39: ㎡ | AG39: =基本入力!AG52 -> 0 | AM39: =基本入力!AL52 -> 0 | AR39: 分の | AT39: =基本入力!AT52 -> 0
B41: 敷地権登記 | H41: =基本入力!R54 -> ■ | I41: 有 | K41: ・ | L41: =基本入力!V54 -> □ | M41: 無 | P41: 実測面積 | U41: =基本入力!AR54 -> - | AC41: ㎡ | AE41: 合計 | AJ41: =基本入力!AB54 -> 1 | AL41: 筆 | AN41: =基本入力!AG54 -> 0 | AV41: ㎡
B43: =VLOOKUP(基本入力!R54,'売契（一般法人）'!DF26:DZ28,20) -> 敷地権の種類が借地権（地上権、賃借権）の場合 | H43: 土地所有者 | N43: 住所 | Q43: =IFERROR(基本入力!I63,"") -> 0
N45: 氏名 | Q45: =IFERROR(基本入力!AL63,"") -> 0
H47: 目的 | K47: =基本入力!AF61 -> 0 | AA47: 期限 | AD47: =IFERROR(基本入力!AA65,"") -> 0 | AG47: =IFERROR(基本入力!AD65,"") -> 0 | AK47: 年 | AM47: =IFERROR(基本入力!AJ65,"") -> 0 | AO47: 月 | AQ47: =IFERROR(基本入力!AN65,"") -> 0 | AS47: 日まで
BH48: 売主 | BK48: =基本入力!AH103 -> ●登記名義人 | CD48: と買主 | CH48: =基本入力!F13 -> ●買主太郎 | DA48: とは
H49: 種類 | K49: =IFERROR(基本入力!B59,"") -> □ | L49: 1. | M49: 旧法による借地権 | U49: =IFERROR(基本入力!AL59,"") -> □ | V49: 2. | W49: 普通借地権 | AC49: =IFERROR(基本入力!AR59,"") -> □ | AD49: 3. | AE49: 定期借地権 | AK49: 地代 | AN49: 月額 | AQ49: =IFERROR(基本入力!Z61,"") -> 0 | AV49: 円
BH50: =IF(基本入力!AB18="","",VLOOKUP(基本入力!AB18,DF50:DJ52,5,)) -> 表記記載の区分所有建物（以下「本物件」という。）の売買契約を締結した。その証として本契約書を壱通作成し、売主・買主署（記）名押印のうえ、買主が原本を、売主がその写しを保有する。 | DF50: 一通作成 | DJ50: 表記記載の区分所有建物（以下「本物件」という。）の売買契約を締結した。その証として本契約書を壱通作成し、売主・買主署（記）名押印のうえ、買主が原本を、売主がその写しを保有する。
B51: 特記事項 | D51: 余白 | DF51: 二通作成 | DJ51: 表記記載の区分所有建物（以下「本物件」という。）の売買契約を締結した。その証として本契約書を弐通作成し、売主・買主署（記）名押印のうえ、各その壱通を保有する。
DF52: 電子契約 | DJ52: 表記記載の区分所有建物（以下「本物件」という。）の売買契約を締結した。その証として売主と買主は、本書の電磁的記録を作成し、売主及び買主が合意の後電子署名を施し、各自その電磁的記録を保管する。
CO55: =基本入力!F70 -> 令和 | CR55: =基本入力!I70 -> 8 | CT55: 年 | CV55: =基本入力!M70 -> 0 | CX55: 月 | CZ55: =基本入力!Q70 -> 0 | DB55: 日
B58: B | D58: 売買代金および支払い方法等 | BH58: 売主 | BL58: 免許証番号 | BV58: =基本入力!AH116 -> 東京都知事 | CB58: =基本入力!AM116 -> 0 | CD58: 第 | CF58: =基本入力!AQ116 -> 0 | CK58: 号
B60: 売 買 代 金 （第1条） | AE60: 金 | AG60: =基本入力!AA70 -> 0 | AV60: 円 | BL60: 事務所の所在地 | BV60: =基本入力!AH111 -> ●登記名義人住所
B62: （上記売買代金のうち消費税額および地方消費税額の合計額） | AE62: 金 | AG62: =基本入力!AA74 -> 0 | AV62: 円 | BL62: 商号または名称 | BV62: =基本入力!AH109 -> ●登記名義人
B64: 手付金 （第2条） | P64: 本契約締結時支払い | AE64: 金 | AV64: 円 | BL64: 代表者氏名 | BV64: =基本入力!AH120 -> 0
CW65: ㊞
B66: 内 金 （第3条） | K66: 第1回 | U66: 年 | Y66: 月 | AC66: 日 | AE66: 金 | AV66: 円 | BL66: 登 録 番 号 | BV66: =基本入力!AH124 -> 0 | CB66: 第 | CD66: =基本入力!AP124 -> 0 | CK66: 号
K68: 第2回 | U68: 年 | Y68: 月 | AC68: 日 | AE68: 金 | AV68: 円 | BL68: 宅地建物取引士氏名 | BV68: =基本入力!AH122 -> 0
CW69: ㊞
B70: 残代金 （第3条） | P70: =基本入力!O119 -> 令和 | S70: =基本入力!R119 -> 8 | U70: 年 | W70: =基本入力!V119 -> 0 | Y70: 月 | AA70: =基本入力!Z119 -> 0 | AC70: 日 | AE70: 金 | AG70: =AG60-AG64-AG66-AG68 -> 0 | AV70: 円
B72: 引渡日 （第6条） | P72: ■ | Q72: 1. | R72: 売買代金全額受領日 | AC72: □ | AD72: 2.
BH73: 買主 | BL73: 住所
B74: 手付解除期日 （第14条第1項） | P74: =基本入力!O123 -> 0 | S74: =基本入力!R123 -> - | U74: 年 | W74: =基本入力!V123 -> - | Y74: 月 | AA74: =基本入力!Z123 -> - | AC74: 日
B76: 違約金の額 （第15条第2項） | P76: □ | Q76: 1.手付金の額 | X76: ■ | Y76: 2.売買代金の | AF76: =重説!CC492 -> 10 | AH76: ％相当額 | AM76: □ | AN76: 3. | AV76: 円
BL77: 氏名
B78: 融 資 | D78: 融資利用の有無 （第17条） | Q78: =基本入力!O113 -> ■ | R78: 1. | S78: 有 | U78: =基本入力!S113 -> □ | V78: 2. | W78: 無 | CG78: ㊞
D80: 申込先： | I80: =基本入力!B102 -> - | AE80: 融資金額 金 | AL80: =基本入力!M102 -> - | AV80: 円 | BH80: 仲介（媒介）人 | CC80: （この契約書は宅地建物取引業法第37条に定められている書面を兼ねています）
D82: 申込先： | I82: =基本入力!B104 -> - | AE82: 融資金額 金 | AL82: =基本入力!M104 -> - | AV82: 円
BH83: 免許証番号 | BO83: =重説!H20 -> 国土交通大臣 | BU83: =重説!O20 -> (3) | BW83: 第 | BY83: =重説!S20 -> 8684 | CD83: 号
D84: 申込先： | I84: =基本入力!B106 -> - | AE84: 融資金額 金 | AL84: =基本入力!M106 -> - | AV84: 円
BH85: 事務所所在地 | BO85: =重説!H24 -> 東京都新宿区西新宿二丁目6番1号
D86: 申込先： | I86: =基本入力!B108 -> - | AE86: 融資金額 金 | AL86: =基本入力!M108 -> - | AV86: 円
BO87: =重説!H26 -> 新宿住友ビル19階
D88: 申込先： | I88: =基本入力!B110 -> - | AE88: 融資金額 金 | AL88: =基本入力!M110 -> - | AV88: 円
BH89: 商 号 | BO89: =重説!H30 -> 東京マンション株式会社
D90: 融資承認取得期日 （同条第2項） | AE90: =基本入力!O115 -> 令和 | AH90: =基本入力!R115 -> 8 | AJ90: 年 | AL90: =基本入力!V115 -> 0 | AN90: 月 | AP90: =基本入力!Z115 -> 0 | AR90: 日
BH91: 代 表 者 等 | BO91: =重説!H32 -> 代表取締役 髙橋 正臣 | CD91: ㊞
D92: 融資利用の特約に基づく契約解除期日 （同条第2項） | AE92: =基本入力!O117 -> 令和 | AH92: =基本入力!R117 -> 8 | AJ92: 年 | AL92: =基本入力!V117 -> 0 | AN92: 月 | AP92: =基本入力!Z117 -> 0 | AR92: 日
BH93: 登録番号 | BO93: =重説!H34 -> ( 東京 ) | BU93: 第 | BW93: =重説!R34 -> 283685 | CB93: 号
B95: 賃借権譲渡承諾の特約に基づく契約解除期日 （第18条第2項） | AE95: =重説!CN467 -> 0 | AH95: =重説!CQ467 -> - | AJ95: 年 | AL95: =重説!CU467 -> - | AN95: 月 | AP95: =重説!CY467 -> - | AR95: 日 | BH95: 宅地建物取引士 | BS95: =重説!H36 -> 新井 拓馬 | CD95: ㊞
B99: （売買の目的物および売買代金） | BK99: 履行を催告したうえで、その期間内に履行がないときは、本契約を解除することができます。なお、第12条第1項の契約不適合について売主が同条同項第1号の修補または同項第2号の代金減額を遅滞した場合を含めます。
B100: 第1条 | E100: 売主は、買主に対し、表記区分所有建物（以下「建物」といいます。）および表記敷地権の目的である土地の（準）共有持分（以下「土地」といい、建物および土地を総称して「本物件」といいます。）を表記売買代金（以下「売買代金」といいます。）で売渡し、買主は、これを買受けました。
BK102: 2 前項の規定による契約解除において、売主、買主は、その相手方に表記違約金（以下「違約金」といいます。）の支払いを請求することができます。ただし、本契約および社会通念に照らして相手方の責めに帰すことができない事由によるものであるときは、違約金の請求はできません。なお、違約金に関し、現に生じた損害額の多寡を問わず、相手方に違約金の増減を請求することができません。
B104: （手付金）
B105: 第2条 | E105: 買主は、売主に対し、表記手付金（以下「手付金」といいます。）を本契約締結と同時に支払います。
E106: 2 前項の手付金は、表記残代金（以下「残代金」といいます。）支払いのときに、売買代金の一部に無利息にて充当します。
BK107: 3 違約金の支払い、清算は次のとおり行います。
B108: （売買代金の支払いの時期、方法等） | BK108: （1）売主が違約した場合、売主は、買主に対し、すみやかに受領済みの金員を無利息にて返還するとともに、違約金を支払います。 （2）買主が違約した場合、違約金が支払い済みの金員を上回るときは、買主は、売主に対し、すみやかにその差額を支払い、支払い済みの金員が違約金を上回るときは、売主は、買主に対し、受領済みの金員から違約金相当額を控除して、すみやかに残額を無利息にて返還します。
B109: 第3条 | E109: 買主は、売主に対し、売買代金として、表記内金（以下「内金」といいます。）、残代金を、表記各支払日までに現金または預金小切手をもって支払います。
B112: （売買対象面積）
B113: 第4条 | E113: 売主、買主は、本物件の売買対象面積は、土地については表記土地面積と、建物については表記建物面積とし、同面積が測量等による面積と差異が生じた場合であっても、互いに異議を申し出ず、売買代金の変更、本契約の解除、損害賠償の請求その他何らの請求もしないものとします。
BH114: （反社会的勢力の排除）
BH115: 第16条 | BK115: 売主、買主は、その相手方に対し、次の各号の事項を確約します。 （1）自らが、暴力団、暴力団関係企業、総会屋もしくはこれらに準ずる者またはその構成員（以下総称して「反社会的勢力」といいます。）ではないこと。 （2）自らの役員（業務を執行する社員、取締役、執行役またはこれらに準ずる者をいいます。）が反社会的勢力ではないこと。 （3）反社会的勢力に自己の名義を利用させ、本契約を締結するものでないこと。 （4）本物件の引渡しおよび売買代金全額の支払いのいずれもが終了するまでの間に、自らまたは第三者を利用して、本契約に関して次の行為をしないこと。 ア 相手方に対する脅迫的な言動または暴力を用いる行為 イ 偽計または威力を用いて相手方の業務を妨害し、または信用を毀損する行為
B117: （所有権等の移転の時期）
B118: 第5条 | E118: 本物件の所有権（敷地権の種類が借地権のときは、建物の所有権と土地に関する借地権。以下「所有権等」といいます。）は、買主が売主に対して売買代金全額を支払い、売主がこれを受領した時に売主から買主に移転します。
B121: （引渡し）
B122: 第6条 | E122: 売主は、買主に対し、本物件を表記引渡日までに引渡します。
B123: （抵当権等の抹消）
B124: 第7条 | E124: 売主は、買主に対し、本物件について、第5条の所有権等の移転時期までにその責任と負担において、先取特権、抵当権等の担保権、地上権、賃借権等の用益権その他名目形式の如何を問わず、買主の完全な所有権等の行使を阻害する一切の負担を除去抹消します。
BK126: 2 売主、買主の一方について、次のいずれかに該当した場合には、その相手方は、何らの催告を要せずして、本契約を解除することができます。 ア 前項（1）または（2）の確約に反する申告をしたことが判明した場合 イ 前項（3）の確約に反し契約をしたことが判明した場合 ウ 前項（4）の確約に反した行為をした場合
B128: （所有権等の移転登記等）
B129: 第8条 | E129: 売主は、買主に対し、売買代金全額の受領と同時に本物件について、買主の名義に、所有権等の移転登記申請手続をします。
E132: 2 前項の登記申請に要する費用は、買主の負担とします。ただし、本物件に関し、前項の所有権等移転登記申請手続前の所有権等登記名義人の住所、氏名等の変更登記を要する場合の費用は、売主の負担とします。 | BK132: 3 買主は、売主に対し、自らまたは第三者をして本物件を反社会的勢力の事務所その他の活動の拠点に供しないことを確約します。 4 売主は、買主が前項に反した行為をした場合には、何らの催告を要せずして、本契約を解除することができます。 5 第2項または前項の規定により本契約が解除された場合には、解除された者は、その相手方に対し、違約金（損害賠償額の予定）として売買代金の20％相当額を支払います。 6 第2項または第4項の規定により本契約が解除された場合には、解除された者は、解除により生じる損害について、その相手方に対し一切の請求をすることができません。 7 第2項および第4項の規定による解除については第15条第1項を適用せず、第5項の違約金および前項の規定については第15条第2項を適用しません。 8 買主が第3項の規定に違反し、本物件を反社会的勢力の事務所その他の活動の拠点に供したと認められる場合において、売主が第4項の規定により本契約を解除するときは、買主は、売主に対し、第5項の違約金に加え、売買代金の80％相当額の違約罰を制裁金として支払います。
B135: （引渡し完了前の滅失・損傷）
B136: 第9条 | E136: 売主、買主は、本物件の引渡し完了前に天災地変、その他売主、買主いずれの責めにも帰すことのできない事由により、本物件が滅失または損傷して、修補が不能、または修補に過大な費用を要し、本契約の履行が不可能となったとき、互いに書面により通知して、本契約を解除することができます。また、買主は、本契約が解除されるまでの間、売買代金の支払いを拒むことができます。 2 本物件の引渡し完了前に、前項の事由によって本物件が損傷した場合であっても、修補することにより本契約の履行が可能であるときは、売主は、本物件を修補して買主に引渡します。 3 第1項の規定により本契約が解除されたとき、売主は、買主に対し、受領済みの金員を無利息にてすみやかに返還します。
BH145: （融資利用の特約）
B146: （物件状況等報告書） | BH146: 第17条 | BK146: 買主は、売買代金に関して、表記融資金を利用するとき、本契約締結後すみやかにその融資の申込み手続をします。
B147: 第10条 | E147: 売主は、買主に対し、本物件について、本契約締結時における状況等を別紙「物件状況等報告書（告知書）」に記載して説明します。
BK148: 2 表記融資承認取得期日までに、前項の融資の全部または一部の金額につき承認が得られないとき、または否認されたとき、買主は、売主に対し、表記契約解除期日までであれば、本契約を解除することができます。
B150: （公租公課等の分担）
B151: 第11条 | E151: 売主、買主は、本物件から生ずる収益または本物件に対して賦課される固定資産税、都市計画税等の公租公課ならびに管理費および修繕積立金等、ガス、水道、電気料金および各種負担金等の諸負担について、引渡完了日の前日までの分を売主の収益または負担とし、引渡完了日以降の分を買主の収益または負担として、引渡完了日において清算します。なお、公租公課の起算日は1月1日とし、売主に管理費および修繕積立金等の滞納があった場合にはその額を売買代金額から控除の上、買主においてこれを支払うこととします。 | BK151: 3 前項により本契約が解除されたとき、売主は、買主に対し、受領済みの金員を無利息にてすみやかに返還します。
BK152: 4 買主が第1項の規定による融資の申込み手続を行わず、または故意に融資の承認を妨げた場合は、第2項の規定による解除はできません。
BH155: （敷地権が賃借権の場合の特約）
BH156: 第18条 | BK156: 売主は、敷地権の種類が賃借権のとき、当該賃借権を買主に譲渡することについて、土地所有者の賃借権譲渡承諾書を取得します。なお、承諾料は売主の負担とします。
B157: （契約不適合による修補請求、代金減額請求および損害賠償請求）
B158: 第12条 | E158: 売主は、買主に対し、引渡された本物件が種類または品質に関して契約の内容に適合しないもの（以下「契約不適合」といいます。）であるときは、責任を負うものとし、買主は、売主に対し、次のとおり請求することができます。
BK159: 2 前項の賃借権譲渡承諾書を交付できないとき、売主は、買主に対し、本契約を表記賃借権譲渡承諾の特約に基づく契約解除期日までであれば、書面による通知により解除することができます。
E161: （1）買主は、売主に対し、本物件の修補を請求することができます。ただし、売主は、買主に不相当な負担を課すものではないときは、買主が請求した方法と異なる方法による修補をすることができます。 （2）前号の場合において、買主が、売主に対し、相当の期間を定めて修補の催告をし、その期間内に修補をしないときは、買主はその不適合の程度に応じて代金の減額を請求することができます。ただし、買主が売主に催告しても修補を受ける見込みがないことが明らかであるときは、催告をすることなく直ちに代金の減額を請求することができます。 （3）第1項の契約不適合が買主の責めに帰すべき事由によるものであるときは、買主は、第1号の修補請求、第2号の代金減額請求のいずれもすることはできません。
...

Sheet 売契（個人)
B1: 一般仲介用 | AN1: 収入印紙
A2: 不 動 産 売 買 契 約 書 | BH2: 建物の構造耐力上主要な部分等の状況について確認した事項（第19条） | CJ2: （ | CK2: 既存の住宅に | CQ2: ■ | CR2: 該当する・ | CW2: □ | CX2: 該当しない | DC2: ）
BH4: 「建物の構造耐力上主要な部分」または「雨水の浸入を防止する部分」の状況について建物状況調査により売主、買主の双方が確認した事項 | CV4: □ | CW4: 1. | CX4: 有 | CZ4: ■ | DA4: 2. | DB4: 無
B7: A | D7: 不動産の表示 | BH7: 確認事項を記載した資料の名称
B9: 一棟の建物の表示 | BH9: 資料作成者 | CF9: 資料作成年月日
B11: 所 在 | I11: =基本入力!J24&基本入力!AB24&基本入力!AD24&基本入力!AG24&基本入力!AJ24 -> 練馬区高松3丁目 ●番地●
B13: 建物の名称 | I13: =基本入力!AB13&基本入力!AB26
B15: 構 造 | I15: =基本入力!J28 -> 鉄筋コンクリート造陸屋根●階建 | AJ15: 延床面積 | AO15: =基本入力!AF28 -> ● | AV15: ㎡ | BH15: 特 約
B17: 専有部分の建物の表示 | BH17: 1 | BJ17: 本物件に関わる管理費・修繕積立金等について滞納分がある場合は、本物件引渡し時までに売主の責任と負担において清算するものとします。以下余白
B19: 家屋番号 | G19: =基本入力!J30&基本入力!R30&基本入力!X30 -> 高松3丁目 ●番●の● | U19: 建物の名称 | AA19: =基本入力!AF30 -> ● | AL19: 種 類 | AQ19: =基本入力!J32 -> 居宅
BJ20: 本契約の成立を証するため、本書の電磁的記録を作成し、売主および買主が合意の後電子署名を施し、各自その電磁的記録を保管する。そのため第20条における印紙は貼付しないものとする。
B21: 構 造 | G21: =基本入力!Q32 -> ●鉄筋コンクリート造1階建 | Y21: 床 面 積 | AD21: =基本入力!AH32 -> ● | AG21: 階部分 | AL21: （登記簿） | AQ21: =基本入力!J34 -> 0 | AV21: ㎡
B23: 附属建物 | G23: （ | H23: =重説!BN25 -> □ | I23: 有 | K23: ・ | L23: =重説!BR25 -> ■ | M23: 無 | O23: ） | P23: =重説!BV25 -> 0
B25: =VLOOKUP(基本入力!R54,'売契（個人)'!DF26:DZ28,2) -> 敷地権の目的である土地の表示 | DF25: 敷地権にチェックあれば「土地」を「敷地権の目的である土地」に「権利の種類」を「敷地権の種類」にする
DF26: ■ | DG26: 敷地権の目的である土地の表示 | DO26: 敷地権の種類 | DT26: 敷地権の割合 ((準)共有持分) | DY26: 敷地権の種類が借地権（地上権、賃借権）の場合
B27: 符号 | D27: 所 在 | P27: 地 番 | U27: 地目（登記簿） | AA27: 地積（登記簿） | AG27: =VLOOKUP(基本入力!R54,'売契（個人)'!DF26:DZ28,10) -> 敷地権の種類 | AM27: =VLOOKUP(基本入力!R54,'売契（個人)'!DF26:DZ28,15) -> 敷地権の割合 ((準)共有持分) | DF27: □ | DG27: 土地の表示 | DO27: 権利の種類 | DT27: 権利の割合 ((準)共有持分) | DY27: 権利の種類が借地権（地上権、賃借権）の場合
B29: 1. | D29: =基本入力!F42 -> 練馬区高松3丁目 | P29: =基本入力!U42 -> ●番● | U29: =基本入力!Y42 -> 宅地 | AA29: =基本入力!AB42 -> ● | AF29: ㎡ | AG29: =基本入力!AG42 -> 0 | AM29: =基本入力!AL42 -> 0 | AR29: 分の | AT29: =基本入力!AT42 -> 0
B31: 2. | D31: =基本入力!F44 -> 0 | P31: =基本入力!U44 -> 0 | U31: =基本入力!Y44 -> 0 | AA31: =基本入力!AB44 -> 0 | AF31: ㎡ | AG31: =基本入力!AG44 -> 0 | AM31: =基本入力!AL44 -> 0 | AR31: 分の | AT31: =基本入力!AT44 -> 0
B33: 3. | D33: =基本入力!F46 -> 0 | P33: =基本入力!U46 -> 0 | U33: =基本入力!Y46 -> 0 | AA33: =基本入力!AB46 -> 0 | AF33: ㎡ | AG33: =基本入力!AG46 -> 0 | AM33: =基本入力!AL46 -> 0 | AR33: 分の | AT33: =基本入力!AT46 -> 0
B35: 4. | D35: =基本入力!F48 -> 0 | P35: =基本入力!U48 -> 0 | U35: =基本入力!Y48 -> 0 | AA35: =基本入力!AB48 -> 0 | AF35: ㎡ | AG35: =基本入力!AG48 -> 0 | AM35: =基本入力!AL48 -> 0 | AR35: 分の | AT35: =基本入力!AT48 -> 0
B37: 5. | D37: =基本入力!F50 -> 0 | P37: =基本入力!U50 -> 0 | U37: =基本入力!Y50 -> 0 | AA37: =基本入力!AB50 -> 0 | AF37: ㎡ | AG37: =基本入力!AG50 -> 0 | AM37: =基本入力!AL50 -> 0 | AR37: 分の | AT37: =基本入力!AT50 -> 0
B39: 6. | D39: =基本入力!F52 -> 0 | P39: =基本入力!U52 -> 0 | U39: =基本入力!Y52 -> 0 | AA39: =基本入力!AB52 -> 0 | AF39: ㎡ | AG39: =基本入力!AG52 -> 0 | AM39: =基本入力!AL52 -> 0 | AR39: 分の | AT39: =基本入力!AT52 -> 0
B41: 敷地権登記 | H41: =基本入力!R54 -> ■ | I41: 有 | K41: ・ | L41: =基本入力!V54 -> □ | M41: 無 | P41: 実測面積 | U41: =基本入力!AR54 -> - | AC41: ㎡ | AE41: 合計 | AJ41: =基本入力!AB54 -> 1 | AL41: 筆 | AN41: =基本入力!AG54 -> 0 | AV41: ㎡
B43: =VLOOKUP(基本入力!R54,'売契（個人)'!DF26:DZ28,20) -> 敷地権の種類が借地権（地上権、賃借権）の場合 | H43: 土地所有者 | N43: 住所 | Q43: =IFERROR(基本入力!I63,"") -> 0
N45: 氏名 | Q45: =IFERROR(基本入力!AL63,"") -> 0
H47: 目的 | K47: =基本入力!AF61 -> 0 | AA47: 期限 | AD47: =IFERROR(基本入力!AA65,"") -> 0 | AG47: =IFERROR(基本入力!AD65,"") -> 0 | AK47: 年 | AM47: =IFERROR(基本入力!AJ65,"") -> 0 | AO47: 月 | AQ47: =IFERROR(基本入力!AN65,"") -> 0 | AS47: 日まで
H49: 種類 | K49: =IFERROR(基本入力!B59,"") -> □ | L49: 1. | M49: 旧法による借地権 | U49: =IFERROR(基本入力!AL59,"") -> □ | V49: 2. | W49: 普通借地権 | AC49: =IFERROR(基本入力!AR59,"") -> □ | AD49: 3. | AE49: 定期借地権 | AK49: 地代 | AN49: 月額 | AQ49: =IFERROR(基本入力!Z61,"") -> 0 | AV49: 円
B51: 特記事項 | D51: 余白
BH54: 売主 | BK54: =基本入力!AH103 -> ●登記名義人 | CD54: と買主 | CH54: =基本入力!F13 -> ●買主太郎 | DA54: とは
BH56: =IF(基本入力!AB18="","",VLOOKUP(基本入力!AB18,DF56:DJ58,5,)) -> 表記記載の区分所有建物（以下「本物件」という。）の売買契約を締結した。その証として本契約書を壱通作成し、売主・買主署（記）名押印のうえ、買主が原本を、売主がその写しを保有する。 | DF56: 一通作成 | DJ56: 表記記載の区分所有建物（以下「本物件」という。）の売買契約を締結した。その証として本契約書を壱通作成し、売主・買主署（記）名押印のうえ、買主が原本を、売主がその写しを保有する。
DF57: 二通作成 | DJ57: 表記記載の区分所有建物（以下「本物件」という。）の売買契約を締結した。その証として本契約書を弐通作成し、売主・買主署（記）名押印のうえ、各その壱通を保有する。
B58: B | D58: 売買代金および支払い方法等 | DF58: 電子契約 | DJ58: 表記記載の区分所有建物（以下「本物件」という。）の売買契約を締結した。その証として売主と買主は、本書の電磁的記録を作成し、売主及び買主が合意の後電子署名を施し、各自その電磁的記録を保管する。
B60: 売 買 代 金 （第1条） | AE60: 金 | AG60: =基本入力!AA70 -> 0 | AV60: 円
CO61: =基本入力!F70 -> 令和 | CR61: =基本入力!I70 -> 8 | CT61: 年 | CV61: =基本入力!M70 -> 0 | CX61: 月 | CZ61: =基本入力!Q70 -> 0 | DB61: 日
B62: （上記売買代金のうち消費税額および地方消費税額の合計額） | AE62: 金 | AG62: =基本入力!AA74 -> 0 | AV62: 円
B64: 手付金 （第2条） | P64: 本契約締結時支払い | AE64: 金 | AG64: =基本入力!AA72 -> 0 | AV64: 円 | BH64: 売主 | BL64: 住所
B66: 内 金 （第3条） | K66: 第1回 | U66: 年 | Y66: 月 | AC66: 日 | AE66: 金 | AV66: 円
K68: 第2回 | U68: 年 | Y68: 月 | AC68: 日 | AE68: 金 | AV68: 円 | BL68: 氏名
CG69: ㊞
B70: 残代金 （第3条） | P70: =基本入力!O119 -> 令和 | S70: =基本入力!R119 -> 8 | U70: 年 | W70: =基本入力!V119 -> 0 | Y70: 月 | AA70: =基本入力!Z119 -> 0 | AC70: 日 | AE70: 金 | AG70: =AG60-AG64-AG66-AG68 -> 0 | AV70: 円
B72: 引渡日 （第6条） | P72: ■ | Q72: 1. | R72: 売買代金全額受領日 | AC72: □ | AD72: 2. | BH72: 買主 | BL72: 住所
B74: 手付解除期日 （第14条第1項） | P74: =基本入力!O123 -> 0 | S74: =基本入力!R123 -> - | U74: 年 | W74: =基本入力!V123 -> - | Y74: 月 | AA74: =基本入力!Z123 -> - | AC74: 日
B76: 違約金の額 （第15条第2項） | P76: □ | Q76: 1.手付金の額 | X76: ■ | Y76: 2.売買代金の | AF76: =重説!CC492 -> 10 | AH76: ％相当額 | AM76: □ | AN76: 3. | AV76: 円 | BL76: 氏名
CG77: ㊞
B78: 融 資 | D78: 融資利用の有無 （第17条） | Q78: =基本入力!O113 -> ■ | R78: 1. | S78: 有 | U78: =基本入力!S113 -> □ | V78: 2. | W78: 無
BH79: 仲介（媒介）人 | CC79: （この契約書は宅地建物取引業法第37条に定められている書面を兼ねています）
D80: 申込先： | I80: =基本入力!B102 -> - | AE80: 融資金額 金 | AL80: =基本入力!M102 -> - | AV80: 円
D82: 申込先： | I82: =基本入力!B104 -> - | AE82: 融資金額 金 | AL82: =基本入力!M104 -> - | AV82: 円
BH83: 免許証番号 | BO83: =重説!$H$20 -> 国土交通大臣 | BU83: =重説!$O$20 -> (3) | BW83: 第 | BY83: =重説!$S$20 -> 8684 | CD83: 号 | CF83: 免許証番号 | CM83: =基本入力!AH116 -> 東京都知事 | CS83: =基本入力!AM116 -> 0 | CU83: 第 | CW83: =基本入力!AQ116 -> 0 | DB83: 号
D84: 申込先： | I84: =基本入力!B106 -> - | AE84: 融資金額 金 | AL84: =基本入力!M106 -> - | AV84: 円
BH85: 事務所所在地 | BO85: =重説!$H$24 -> 東京都新宿区西新宿二丁目6番1号 | CF85: 事務所所在地 | CM85: =基本入力!AH111 -> ●登記名義人住所
D86: 申込先： | I86: =基本入力!B108 -> - | AE86: 融資金額 金 | AL86: =基本入力!M108 -> - | AV86: 円
BO87: =重説!$H$26 -> 新宿住友ビル19階
D88: 申込先： | I88: =基本入力!B110 -> - | AE88: 融資金額 金 | AL88: =基本入力!M110 -> - | AV88: 円
BH89: 商 号 | BO89: =重説!$H$30 -> 東京マンション株式会社 | CF89: 商 号 | CM89: =基本入力!AH109 -> ●登記名義人
D90: 融資承認取得期日 （同条第2項） | AE90: =基本入力!O115 -> 令和 | AH90: =基本入力!R115 -> 8 | AJ90: 年 | AL90: =基本入力!V115 -> 0 | AN90: 月 | AP90: =基本入力!Z115 -> 0 | AR90: 日
BH91: 代 表 者 等 | BO91: =重説!$H$32 -> 代表取締役 髙橋 正臣 | CD91: ㊞ | CF91: 代 表 者 等 | CM91: =基本入力!AH120 -> 0 | DB91: ㊞
D92: 融資利用の特約に基づく契約解除期日 （同条第2項） | AE92: =基本入力!O117 -> 令和 | AH92: =基本入力!R117 -> 8 | AJ92: 年 | AL92: =基本入力!V117 -> 0 | AN92: 月 | AP92: =基本入力!Z117 -> 0 | AR92: 日
BH93: 登録番号 | BO93: =重説!$H$34 -> ( 東京 ) | BU93: 第 | BW93: =重説!$R$34 -> 283685 | CB93: 号 | CF93: 登録番号 | CM93: =基本入力!AH124 -> 0 | CS93: 第 | CU93: =基本入力!AP124 -> 0 | CZ93: 号
B95: 賃借権譲渡承諾の特約に基づく契約解除期日 （第18条第2項） | AE95: =重説!CN467 -> 0 | AH95: =重説!CQ467 -> - | AJ95: 年 | AL95: =重説!CU467 -> - | AN95: 月 | AP95: =重説!CY467 -> - | AR95: 日 | BH95: 宅地建物取引士 | BS95: ='売契（業者）'!BS95:CC96 -> 新井 拓馬 | CD95: ㊞ | CF95: 宅地建物取引士 | CQ95: =基本入力!AH122 -> 0 | DB95: ㊞
DF97: ↓契約不適合責任負わないバージョン
B99: （売買の目的物および売買代金） | BK99: 2 前項の規定による契約解除において、売主、買主は、その相手方に表記違約金（以下「違約金」といいます。）の支払いを請求することができます。ただし、本契約および社会通念に照らして相手方の責めに帰すことができない事由によるものであるときは、違約金の請求はできません。なお、違約金に関し、現に生じた損害額の多寡を問わず、相手方に違約金の増減を請求することができません。 | DF99: （契約不適合による修補請求）
B100: 第1条 | E100: 売主は、買主に対し、表記区分所有建物（以下「建物」といいます。）および表記敷地権の目的である土地の（準）共有持分（以下「土地」といい、建物および土地を総称して「本物件」といいます。）を表記売買代金（以下「売買代金」といいます。）で売渡し、買主は、これを買受けました。 | DF100: 第12条 | DI100: 売主は、買主に対し、民法、商法および本契約の他の条項にかかわらず、引渡された建物の品質に関して契約の内容に適合しないもの（以下「契約不適合」といいます。）について、一切の契約不適合責任を負いません。
DI103: 2 買主は、売主に対し、前項の契約不適合について、修補の請求、本契約の無効の主張、本契約の解除、売買代金の減額請求および損害賠償の請求をすることはできません。
B104: （手付金） | BK104: 3 違約金の支払い、清算は次のとおり行います。 （1）売主が違約した場合、売主は、買主に対し、すみやかに受領済みの金員を無利息にて返還するとともに、違約金を支払います。 （2）買主が違約した場合、違約金が支払い済みの金員を上回るときは、買主は、売主に対し、すみやかにその差額を支払い、支払い済みの金員が違約金を上回るときは、売主は、買主に対し、受領済みの金員から違約金相当額を控除して、すみやかに残額を無利息にて返還します。
B105: 第2条 | E105: 買主は、売主に対し、表記手付金（以下「手付金」といいます。）を本契約締結と同時に支払います。
E106: 2 前項の手付金は、表記残代金（以下「残代金」といいます。）支払いのときに、売買代金の一部に無利息にて充当します。
DF107: （契約違反による解除・違約金）
B108: （売買代金の支払いの時期、方法等） | DF108: 第15条 | DI108: 売主、買主は、その相手方が本契約にかかる債務の履行を遅滞したとき、その相手方に対し、相当の期間を定めて債務の履行を催告したうえで、その期間内に履行がないときは、本契約を解除することができます。
B109: 第3条 | E109: 買主は、売主に対し、売買代金として、表記内金（以下「内金」といいます。）、残代金を、表記各支払日までに現金または預金小切手をもって支払います。
B112: （売買対象面積）
B113: 第4条 | E113: 売主、買主は、本物件の売買対象面積は、土地については表記土地面積と、建物については表記建物面積とし、同面積が測量等による面積と差異が生じた場合であっても、互いに異議を申し出ず、売買代金の変更、本契約の解除、損害賠償の請求その他何らの請求もしないものとします。 | BH113: （反社会的勢力の排除）
BH114: 第16条 | BK114: 売主、買主は、その相手方に対し、次の各号の事項を確約します。 （1）自らが、暴力団、暴力団関係企業、総会屋もしくはこれらに準ずる者またはその構成員（以下総称して「反社会的勢力」といいます。）ではないこと。 （2）自らの役員（業務を執行する社員、取締役、執行役またはこれらに準ずる者をいいます。）が反社会的勢力ではないこと。 （3）反社会的勢力に自己の名義を利用させ、本契約を締結するものでないこと。 （4）本物件の引渡しおよび売買代金全額の支払いのいずれもが終了するまでの間に、自らまたは第三者を利用して、本契約に関して次の行為をしないこと。 ア 相手方に対する脅迫的な言動または暴力を用いる行為 イ 偽計または威力を用いて相手方の業務を妨害し、または信用を毀損する行為
B117: （所有権等の移転の時期）
B118: 第5条 | E118: 本物件の所有権（敷地権の種類が借地権のときは、建物の所有権と土地に関する借地権。以下「所有権等」といいます。）は、買主が売主に対して売買代金全額を支払い、売主がこれを受領した時に売主から買主に移転します。
B121: （引渡し）
B122: 第6条 | E122: 売主は、買主に対し、本物件を表記引渡日までに引渡します。
B124: （抵当権等の抹消）
B125: 第7条 | E125: 売主は、買主に対し、本物件について、第5条の所有権等の移転時期までにその責任と負担において、先取特権、抵当権等の担保権、地上権、賃借権等の用益権その他名目形式の如何を問わず、買主の完全な所有権等の行使を阻害する一切の負担を除去抹消します。 | BK125: 2 売主、買主の一方について、次のいずれかに該当した場合には、その相手方は、何らの催告を要せずして、本契約を解除することができます。 ア 前項（1）または（2）の確約に反する申告をしたことが判明した場合 イ 前項（3）の確約に反し契約をしたことが判明した場合 ウ 前項（4）の確約に反した行為をした場合
B129: （所有権等の移転登記等）
B130: 第8条 | E130: 売主は、買主に対し、売買代金全額の受領と同時に本物件について、買主の名義に、所有権等の移転登記申請手続をします。 2 前項の登記申請に要する費用は、買主の負担とします。ただし、本物件に関し、前項の所有権等移転登記申請手続前の所有権等登記名義人の住所、氏名等の変更登記を要する場合の費用は、売主の負担とします。
BK131: 3 買主は、売主に対し、自らまたは第三者をして本物件を反社会的勢力の事務所その他の活動の拠点に供しないことを確約します。 4 売主は、買主が前項に反した行為をした場合には、何らの催告を要せずして、本契約を解除することができます。 5 第2項または前項の規定により本契約が解除された場合には、解除された者は、その相手方に対し、違約金（損害賠償額の予定）として売買代金の20％相当額を支払います。 6 第2項または第4項の規定により本契約が解除された場合には、解除された者は、解除により生じる損害について、その相手方に対し一切の請求をすることができません。 7 第2項および第4項の規定による解除については第15条第1項を適用せず、第5項の違約金および前項の規定については第15条第2項を適用しません。
B135: （引渡し完了前の滅失・損傷）
B136: 第9条 | E136: 売主、買主は、本物件の引渡し完了前に天災地変、その他売主、買主いずれの責めにも帰すことのできない事由により、本物件が滅失または損傷して、修補が不能、または修補に過大な費用を要し、本契約の履行が不可能となったとき、互いに書面により通知して、本契約を解除することができます。また、買主は、本契約が解除されるまでの間、売買代金の支払いを拒むことができます。 2 本物件の引渡し完了前に、前項の事由によって本物件が損傷した場合であっても、修補することにより本契約の履行が可能であるときは、売主は、本物件を修補して買主に引渡します。 3 第1項の規定により本契約が解除されたとき、売主は、買主に対し、受領済みの金員を無利息にてすみやかに返還します。
BK141: 8 買主が第3項の規定に違反し、本物件を反社会的勢力の事務所その他の活動の拠点に供したと認められる場合において、売主が第4項の規定により本契約を解除するときは、買主は、売主に対し、第5項の違約金に加え、売買代金の80％相当額の違約罰を制裁金として支払います。 | DF141: ←黄色に塗ってあるのは売主が個人の時と業者の時で内容が違う部分
B145: （物件状況等報告書） | BH145: （融資利用の特約）
B146: 第10条 | E146: 売主は、買主に対し、本物件について、本契約締結時における状況等を別紙「物件状況等報告書（告知書）」に記載して説明します。 | BH146: 第17条 | BK146: 買主は、売買代金に関して、表記融資金を利用するとき、本契約締結後すみやかにその融資の申込み手続をします。
BK148: 2 表記融資承認取得期日までに、前項の融資の全部または一部の金額につき承認が得られないとき、または否認されたとき、買主は、売主に対し、表記契約解除期日までであれば、本契約を解除することができます。
B149: （公租公課等の分担）
B150: 第11条 | E150: 売主、買主は、本物件から生ずる収益または本物件に対して賦課される固定資産税、都市計画税等の公租公課ならびに管理費および修繕積立金等、ガス、水道、電気料金および各種負担金等の諸負担について、引渡完了日の前日までの分を売主の収益または負担とし、引渡完了日以降の分を買主の収益または負担として、引渡完了日において清算します。なお、公租公課の起算日は1月1日とし、売主に管理費および修繕積立金等の滞納があった場合にはその額を売買代金額から控除の上、買主においてこれを支払うこととします。
BK151: 3 前項により本契約が解除されたとき、売主は、買主に対し、受領済みの金員を無利息にてすみやかに返還します。
BK152: 4 買主が第1項の規定による融資の申込み手続を行わず、または故意に融資の承認を妨げた場合は、第2項の規定による解除はできません。
BH155: （敷地権が賃借権の場合の特約）
B156: （契約不適合による修補請求） | BH156: 第18条 | BK156: 売主は、敷地権の種類が賃借権のとき、当該賃借権を買主に譲渡することについて、土地所有者の賃借権譲渡承諾書を取得します。なお、承諾料は売主の負担とします。
B157: 第12条 | E157: 売主は、買主に対し、引渡された建物の専有部分が次に該当する場合は、品質に関して契約の内容に適合しないもの（以下「契約不適合」といいます。）として、引渡完了日から3ヶ月以内に通知を受けたものにかぎり、契約不適合責任を負い、それ以外の建物の契約不適合および土地の契約不適合ならびに共用部分に原因がある契約不適合について、責任を負いません。 （1） シロアリの害 （2） 給排水管の故障
BK159: 2 前項の賃借権譲渡承諾書を交付できないとき、売主は、買主に対し、本契約を表記賃借権譲渡承諾の特約に基づく契約解除期日までであれば、書面による通知により解除することができます。
BK162: 3 前項により本契約を解除したとき、売主は、買主に対し、受領済みの金員を無利息にてすみやかに返還します。
E163: 2 売主が、買主に対し負う前項の契約不適合責任の内容は、修補にかぎるものとし、買主は、売主に対し、前項の契約不適合について、修補の請求以外に、本契約の無効の主張、本契約の解除、売買代金の減額請求および損害賠償の請求をすることはできません。
BH164: （建物の構造耐力上主要な部分等の状況について双方が確認した事項）
BH165: 第19条 | BK165: 売主、買主は、建物の構造耐力上主要な部分等の状況について双方が確認した事項がある場合には、表記のとおりであることを確認します。
...

Sheet 特約・容認事項
B2: 【容認事項】

Sheet 特約・容認事項A3
B2: 【容認事項】

Sheet 売媒介
B2: この媒介契約は、国土交通省が定めた標準媒介契約約款に基づく契約です。 | AM2: 依頼の内容 | AS2: 売却 | BI2: 5 | BK2: 建物状況調査を実施する者のあっせんの有無 | CG2: （ | CH2: □ | CI2: 有 | CK2: ・ | CL2: ■ | CM2: 無 | CO2: ： | DB2: ）
B4: 一 般 媒 介 契 約 書 | BK4: あっせん無の理由 | BW4: 目的物件の所有者から、建物状況調査の実施の同意が得られないため
BI6: 6 | BK6: 指定流通機構への登録の有無 | BX6: （ | BY6: □ | BZ6: 有 | CB6: ・ | CC6: ■ | CD6: 無 | CF6: ）
C7: この契約は、次の３つの契約型式のうち、一般媒介契約型式です。なお、依頼者は、重ねて依頼する宅地建物取引業者を明示する義務を負います。重ねて依頼する宅地建物取引業者を明示しない契約とする場合は、その旨を特約するものとします。 ●専属専任媒介契約型式 依頼者は、目的物件の売買又は交換の媒介又は代理を、当社以外の宅地建物取引業者に重ねて依頼することができません。 依頼者は、自ら発見した相手方と売買又は交換の契約を締結することができません。 当社は、目的物件を国土交通大臣が指定した指定流通機構に登録します。 ●専任媒介契約型式 依頼者は、目的物件の売買又は交換の媒介又は代理を、当社以外の宅地建物取引業者に重ねて依頼することができません。 依頼者は、自ら発見した相手方と売買又は交換の契約を締結することができます。 当社は、目的物件を国土交通大臣が指定した指定流通機構に登録します。 ●一般媒介契約型式 依頼者は、目的物件の売買又は交換の媒介又は代理を、当社以外の宅地建物取引業者に重ねて依頼することができます。 依頼者は、自ら発見した相手方と売買又は交換の契約を締結することができます。
BX8: ＊登録をする場合にあっては、当該登録をしようとする指定流通機構の名称を記入する。
BI10: 7 | BK10: 有効期間 | BQ10: この媒介契約締結後 | BZ10: 3 | CB10: ヶ月（ | CE10: =基本入力!F72 -> 令和 | CI10: =IF(基本入力!I72=0,"",基本入力!I72) -> 9 | CK10: 年 | CM10: =IF(基本入力!M72=0,"",基本入力!M72) -> -9 | CO10: 月 | CQ10: =IF(基本入力!Q72=0,"",基本入力!Q72) | CS10: 日まで）とします。
BI12: 8 | BK12: 約定報酬額 | BX12: (報酬額) | CB12: =基本入力!E84 | CK12: 円とします。
BI14: 9 | BK14: 約定報酬の受領の時期 | BX14: 目的物件の引渡時(残代金支払時)に一括払いとします。
BI16: 10 | BK16: 特約事項 | BX16: （ | DD16: ）
BI20: 別表
BI22: 所 有 者 | BK22: 住 所 | BO22: =基本入力!AH105 -> ●登記名義人住所 | CG22: 登記名義人 | CI22: 住 所 | CM22: =基本入力!AH105 -> ●登記名義人住所
BK26: 氏 名 | BO26: =基本入力!AH103 -> ●登記名義人 | CI26: 氏 名 | CM26: =基本入力!AH103 -> ●登記名義人
B29: 依頼者甲は、この契約書および一般媒介契約約款により、別表に表示する不動産(目的物件)に関する売買(交換)の媒介を宅地建物取引業者乙に依頼し、乙はこれを承諾します。
BI31: 所在地 | BK31: =基本入力!J24&基本入力!AB24&基本入力!AD24&基本入力!AG24&基本入力!AJ24 -> 練馬区高松3丁目 ●番地●
AH32: =基本入力!F70 -> 令和 | AL32: =IF(基本入力!I70=0,"",基本入力!I70) -> 8 | AN32: 年 | AP32: =IF(基本入力!M70=0,"",基本入力!M70) | AR32: 月 | AT32: =IF(基本入力!Q70=0,"",基本入力!Q70) | AV32: 日
B35: 甲 | D35: ・ | E35: 依 頼 者 | N35: 住 所
BI36: 目 的 物 件 の 表 示 | BK36: 土 地 | BM36: 実 測 | CA36: ㎡ | CC36: 地 目 | CE36: □ | CF36: 宅地・ | CI36: □ | CJ36: 田・ | CL36: □ | CM36: 畑・ | CO36: 権利内容
CQ37: □ | CR37: 所有権 ・ | CW37: □ | CX37: 借地権
N38: 氏 名 | CE38: □ | CF38: 山林・ | CI38: □ | CJ38: 雑種地・
AW39: ㊞ | BM39: 公 簿 | CA39: ㎡
CE40: □ | CF40: その他 | CJ40: （ | CN40: ）
B41: 乙 | D41: ・ | E41: 宅地建物取引業者 | N41: 商号（名称） | X41: =重説!H30 -> 東京マンション株式会社
BK42: 建 物 | BM42: 建 築 面 積 | CA42: ㎡ | CC42: 種類 | CO42: 構造 | DC42: 造
N43: 代表者 | X43: =重説!H32 -> 代表取締役 髙橋 正臣
AW44: ㊞ | CV44: 葺 | DB44: 階建
N45: 主たる事務所の所在地 | X45: =重説!H24&" "&重説!H26 -> 東京都新宿区西新宿二丁目6番1号 新宿住友ビル19階
BM46: 延面積 | CA46: ㎡ | CC46: 間取り
N47: 免許証番号 | X47: =重説!H20 -> 国土交通大臣 | AF47: =重説!O20 -> (3) | AH47: 第 | AJ47: =重説!S20 -> 8684 | AO47: 号
B50: 1 | D50: 依頼する乙以外の宅地建物取引業者 | BK50: マンション | BM50: 名 称 | BR50: =基本入力!AB13 -> 0 | CH50: 構 造 | CM50: =基本入力!Q32 -> ●鉄筋コンクリート造1階建
E52: （商号または名称） | BR52: =基本入力!AH32 -> ● | BY52: 階 | CA52: =基本入力!AS13 -> ● | CE52: 号室 | CH52: タイプ | CM52: =基本入力!AJ15 -> ● | CV52: =基本入力!AL15 -> ＬＤＫ
E54: （主たる事務所の所在地） | BM54: 専 有 面 積 | BU54: 登記簿 | CA54: =基本入力!J34 -> 0 | CF54: ㎡ | CH54: 共有持分 | CM54: =IF(基本入力!AL42=0,"",基本入力!AL42) | CV54: 分の | CY54: =IF(基本入力!AT42=0,"",基本入力!AT42)
B56: 2 | D56: 甲の通知義務 | BU56: 壁芯 | CA56: =基本入力!AS15 -> - | CF56: ㎡
C58: 一 | E58: 甲は、この媒介契約の有効期間内に1に表示する宅地建物取引業者以外の宅地建物取引業者に重ねて目的物件の売買または交換の媒介または代理を依頼しようとするときは、乙に対して、その旨を通知する義務を負います。
BI59: 本 体 価 額 | BT59: 金 | BV59: =基本入力!AO70 -> 0 | CG59: 円 | CJ59: 備 考 | CL59: （その他の業務） 評価証明書、公課証明書取得に関する一切の権限 管理に係る調査報告書取得に関する一切の権限
C62: 二 | E62: 甲は、この媒介契約の有効期間内に、自ら発見した相手方と売買もしくは交換の契約を締結したとき、または乙以外の宅地建物取引業者の媒介もしくは代理によって売買もしくは交換の契約を締結させたときは、乙に対して、遅滞なくその旨を通知する義務を負います。 | BI62: 消費税額および 地方消費税額の合計額 | BT62: 金 | BV62: =基本入力!AA74 -> 0 | CG62: 円
C66: 三 | E66: 一および二の通知を怠った場合には、乙は、一般媒介契約約款の定めにより、甲に対して、費用の償還を請求することができます。 | BI66: 媒 介 価 額 | BT66: 総額 | BW66: 金 | BY66: =基本入力!AA70 -> 0 | CG66: 円
B69: 3 | D69: 成約に向けての乙の義務 | BI69: [ ただし、買い依頼に係る媒介契約については、次の別表を使用することとして差支えない。]
C71: 一 | E71: 乙は、契約の相手方との契約条件の調整等を行い、契約の成立に向けて積極的に努力します。
BI72: 希望する条件
C73: 二 | E73: 乙は、目的物件の売買又は交換の申込みがあったときは、甲に対し、遅滞なく、その旨を報告します。
BI74: 項 目 | BT74: 内 容 | CU74: 希 望 の 程 度
B75: 4 | D75: 媒介に係る乙の業務
BI76: 物 件 の 種 類 | CU76: 普通
D77: 乙は、3に掲げる義務を履行するとともに、次の業務を行います。
BI78: 価 額 | CU78: 普通
C79: 一 | E79: 乙は、甲に対し、目的物件を売買すべき価額または評価額について意見を述べるときは、その根拠を明らかにして説明を行います。
BI80: 広 さ ・ 間 取 り 等 | CU80: 普通
C82: 二 | E82: 甲が乙に目的物件の購入または取得を依頼した場合にあっては、乙は、甲に対し、目的物件の売買または交換の契約が成立するまでの間に、宅地建物取引士をして、宅地建物取引業法第35条に定める重要事項について、宅地建物取引士が記名押印した書面を交付して説明させます。 | BI82: 物 件 の 所 在 地 | CU82: 普通
BI85: そ の 他 の 条 件 （希望の程度も お書き下さい。）
C86: 三 | E86: 乙は、目的物件の売買または交換の契約が成立したときは、甲および甲の相手方に対し、遅滞なく、宅地建物取引業法第37条に定める書面を作成し、宅地建物取引士に当該書面に記名押印させた上で、これを交付します。
C90: 四 | E90: 乙は、甲に対し、登記、決済手続等の目的物件の引渡しに係る事務の補助を行います。 | BI90: 注） 「希望の程度」の欄には、「特に強い」、「やや強い」、「普通」等と記入すること。
B94: 一 般 媒 介 契 約 約 款 | BI94: （直接取引）
BI95: 第13条 | BM95: 一般媒介契約の有効期間内または有効期間の満了後2年以内に、甲が乙の紹介によって知った相手方と乙を排除して目的物件の売買または交換の契約を締結したときは、乙は、甲に対して、契約の成立に寄与した割合に応じた相当額の報酬を請求することができます。
B97: （目的）
B98: 第1条 | F98: この約款は、宅地または建物の売買または交換の一般媒介契約について、当事者が契約の締結に際して定めるべき事項および当事者が契約の履行に関して互いに遵守すべき事項を明らかにすることを目的とします。
BI99: （費用償還の請求）
BI100: 第14条 | BM100: 一般媒介契約の有効期間内に甲が乙に明示していない宅地建物取引業者に目的物件の売買または交換の媒介または代理を依頼し、これによって売買または交換の契約を成立させたときは、乙は、甲に対して、一般媒介契約の履行のために要した費用の償還を請求することができます。
B101: （当事者の表示と用語の定義）
B102: 第2条 | F102: この約款においては、媒介契約の当事者について、依頼者を「甲」、依頼を受ける宅地建物取引業者を「乙」と表示します。
E104: 2 | F104: この約款において、「一般媒介契約」とは、甲が依頼の目的である宅地または建物（以下「目的物件」といいます。）の売買または交換の媒介または代理を乙以外の宅地建物取引業者に重ねて依頼することができるものとする媒介契約をいいます。 | BL104: 2 | BM104: 前項の費用の額は、約定報酬額を超えることはできません。
BI106: （依頼者の通知義務）
B107: （目的物件の表示等） | BI107: 第15条 | BM107: 甲は、一般媒介契約の有効期間内に、自ら発見した相手方と目的物件の売買もしくは交換の契約を締結したとき、または乙以外の宅地建物取引業者の媒介もしくは代理によって目的物件の売買もしくは交換の契約を成立させたときは、乙に対して遅滞なくその旨を通知しなければなりません。
B108: 第3条 | F108: 目的物件を特定するために必要な表示および目的物件を売買すべき価額または交換すべき評価額（以下「媒介価額」といいます。）は、一般媒介契約書の別表に記載します。
B111: （重ねて依頼をする宅地建物取引業者の明示） | BL111: 2 | BM111: 甲が前項の通知を怠った場合において、乙が売買または交換の契約の成立後善意で甲のために一般媒介契約の事務の処理に要する費用を支出したときは、乙は、甲に対して、その費用の償還を請求することができます。
B112: 第4条 | F112: 甲は、目的物件の売買または交換の媒介または代理を乙以外の宅地建物取引業者に重ねて依頼するときは、その宅地建物取引業者を乙に明示しなければなりません。
BI114: （更新）
E115: 2 | F115: 一般媒介契約の締結時においてすでに依頼をしている宅地建物取引業者の商号または名称および主たる事務所の所在地は、一般媒介契約書に記載するものとし、その後において更に他の宅地建物取引業者に依頼をしようとするときは、甲は、その旨を乙に通知するものとします。 | BI115: 第16条 | BM115: 一般媒介契約の有効期間は、甲および乙の合意に基づき、更新することができます。
BL117: 2 | BM117: 有効期間の更新をしようとするときは、有効期間の満了に際して甲から乙に対し文書でその旨を申し出るものとします。
B119: （宅地建物取引業者の義務等） | BL119: 3 | BM119: 前2項の規定による有効期間の更新に当たり、甲乙間で一般媒介契約の内容について別段の合意がなされなかったときは、従前の契約と同一内容の契約が成立したものとみなします。
B120: 第5条 | F120: 乙は、次の事項を履行する義務を負います。
F122: 一 | H122: 契約の相手方を探索するとともに、契約の相手方との契約条件の調整等を行い、契約の成立に向けて積極的に努力すること | BI122: （契約の解除）
BI123: 第17条 | BM123: 甲または乙が一般媒介契約に定める義務の履行に関してその本旨に従った履行をしない場合には、その相手方は、相当の期間を定めて履行を催告し、その期間内に履行がないときは、一般媒介契約を解除することができます。
F125: 二 | H125: 目的物件の売買または交換の申込みがあったときは、甲に対して、遅滞なく、その旨を報告すること
BL126: 2 | BM126: 次のいずれかに該当する場合においては、甲は、一般媒介契約を解除することができます。
E127: 2 | F127: 乙は、前項に掲げる義務を履行するとともに、次の業務を行います。
BM128: 一 | BO128: 乙が一般媒介契約に係る業務について信義を旨とし誠実に遂行する義務に違反したとき
F129: 一 | H129: 媒介価額の決定に際し、甲に、その価額に関する意見を述べるときは、根拠を示して説明を行うこと
BM130: 二 | BO130: 乙が一般媒介契約に係る重要な事項について故意もしくは重過失により事実を告げず、または不実のことを告げる行為をしたとき
F131: 二 | H131: 甲が乙に目的物件の購入または取得を依頼した場合にあっては、甲に対して、目的物件の売買または交換の契約が成立するまでの間に、宅地建物取引士をして、宅地建物取引業法第35条に定める重要事項について、宅地建物取引士が記名押印した書面を交付して説明させること
BM133: 三 | BO133: 乙が宅地建物取引業に関して不正または著しく不当な行為をしたとき
F135: 三 | H135: 目的物件の売買または交換の契約が成立したときは、甲および甲の相手方に対して、遅滞なく、宅地建物取引業法第37条に定める書面を作成し、宅地建物取引士に当該書面に記名押印させた上で、これを交付すること | BI135: （反社会的勢力の排除）
BI136: 第18条 | BM136: 甲および乙は、それぞれ相手方に対し、次の事項を確約します。
F138: 四 | H138: 甲に対して、登記、決済手続等の目的物件の引渡しに係る事務の補助を行うこと | BM138: 一 | BO138: 自らが、暴力団、暴力団関係企業、総会屋もしくはこれらに準ずる者またはその構成員（以下これらを総称して「反社会的勢力」といいます。）ではないこと
F140: 五 | H140: その他一般媒介契約書に記載する業務を行うこと
BM141: 二 | BO141: 自らの役員（業務を執行する社員、取締役、執行役またはこれらに準ずる者をいいます。）が反社会的勢力ではないこと
B142: （媒介価額の変更の助言等）
B143: 第6条 | F143: 媒介価額が地価や物価の変動その他事情の変更によって不適当と認められるに至ったときは、乙は、甲に対して、媒介価額の変更について根拠を示して助言します。
BM144: 三 | BO144: 反社会的勢力に自己の名義を利用させ、一般媒介契約を締結するものでないこと
E146: 2 | F146: 甲は、媒介価額を変更しようとするときは、乙にその旨を通知します。この場合において、価額の変更が引上げであるとき（甲が乙に目的物件の購入または取得を依頼した場合にあっては、引下げであるとき） は、乙の承諾を要します。 | BM146: 四 | BO146: 一般媒介契約の有効期間内に、自らまたは第三者を利用して、次の行為をしないこと
BO148: イ | BQ148: 相手方に対する脅迫的な言動または暴力を用いる行為
E149: 3 | F149: 乙は、前項の承諾を拒否しようとするときは、その根拠を示さなければなりません。
BO150: ロ | BQ150: 偽計または威力を用いて相手方の業務を妨害し、または信用を毀損する行為
B151: （建物状況調査を実施する者のあっせん）
B152: 第7条 | F152: 乙は、この媒介契約において建物状況調査を実施する者のあっせんを行うこととした場合にあっては甲に対して、建物状況調査を実施する者をあっせんしなければなりません。 | BL152: 2 | BM152: 一般媒介契約の有効期間内に、甲または乙が次のいずれかに該当した場合には、その相手方は、何らの催告を要せずして、一般媒介契約を解除することができます。
B155: （有効期間） | BM155: 一 | BO155: 前項第一号または第二号の確約に反する申告をしたことが判明した場合
B156: 第8条 | F156: 一般媒介契約の有効期間は、3ヶ月を超えない範囲で、甲乙協議の上、定めます。
BM157: 二 | BO157: 前項第三号の確約に反し契約をしたことが判明した場合
B158: （指定流通機構への登録）
B159: 第9条 | F159: 乙は、この媒介契約において目的物件を指定流通機構に登録することとした場合にあっては、当該目的物件を一般媒介契約書に記載する指定流通機構に登録しなければなりません。 | BM159: 三 | BO159: 前項第四号の確約に反する行為をした場合
BL161: 3 | BM161: 乙が前項の規定により一般媒介契約を解除したときは、甲に対して、約定報酬額に相当する金額（すでに約定報酬の一部を受領している場合は、その額を除いた額とします。なお、この媒介に係る消費税額および地方消費税額の合計額に相当する額を除きます。）を違約金として請求することができます。
...

Sheet 買媒介
B2: この媒介契約は、国土交通省が定めた標準媒介契約約款に基づく契約です。 | AM2: 依頼の内容 | AS2: 購入 | BI2: 5 | BK2: 建物状況調査を実施する者のあっせんの有無 | CG2: （ | CH2: □ | CI2: 有 | CK2: ・ | CL2: ■ | CM2: 無 | CO2: ）
B4: 一 般 媒 介 契 約 書 | BK4: あっせん無の理由 | BW4: 目的物件の所有者から、建物状況調査の実施の同意が得られないため
BI6: 6 | BK6: 指定流通機構への登録の有無 | BX6: （ | BY6: □ | BZ6: 有 | CB6: ・ | CC6: ■ | CD6: 無 | CF6: ）
C7: この契約は、次の３つの契約型式のうち、一般媒介契約型式です。なお、依頼者は、重ねて依頼する宅地建物取引業者を明示する義務を負います。重ねて依頼する宅地建物取引業者を明示しない契約とする場合は、その旨を特約するものとします。 ●専属専任媒介契約型式 依頼者は、目的物件の売買又は交換の媒介又は代理を、当社以外の宅地建物取引業者に重ねて依頼することができません。 依頼者は、自ら発見した相手方と売買又は交換の契約を締結することができません。 当社は、目的物件を国土交通大臣が指定した指定流通機構に登録します。 ●専任媒介契約型式 依頼者は、目的物件の売買又は交換の媒介又は代理を、当社以外の宅地建物取引業者に重ねて依頼することができません。 依頼者は、自ら発見した相手方と売買又は交換の契約を締結することができます。 当社は、目的物件を国土交通大臣が指定した指定流通機構に登録します。 ●一般媒介契約型式 依頼者は、目的物件の売買又は交換の媒介又は代理を、当社以外の宅地建物取引業者に重ねて依頼することができます。 依頼者は、自ら発見した相手方と売買又は交換の契約を締結することができます。
BX8: ＊登録をする場合にあっては、当該登録をしようとする指定流通機構の名称を記入する。
BI10: 7 | BK10: 有効期間 | BQ10: この媒介契約締結後 | BZ10: 3 | CB10: ヶ月（ | CE10: =基本入力!F72 -> 令和 | CI10: =IF(基本入力!I72=0,"",基本入力!I72) -> 9 | CK10: 年 | CM10: =IF(基本入力!M72=0,"",基本入力!M72) -> -9 | CO10: 月 | CQ10: =IF(基本入力!Q72=0,"",基本入力!Q72) | CS10: 日まで）とします。
BI12: 8 | BK12: 約定報酬額 | BX12: (報酬額) | CB12: =基本入力!M84 -> 66000 | CK12: 円とします。
BI14: 9 | BK14: 約定報酬の受領の時期 | BX14: 目的物件の引渡時(残代金支払時)に一括払いとします。
BI16: 10 | BK16: 特約事項 | BX16: （ | DD16: ）
BI20: 別表
BI22: 所 有 者 | BK22: 住 所 | BO22: =基本入力!AH105 -> ●登記名義人住所 | CG22: 登記名義人 | CI22: 住 所 | CM22: =基本入力!AH105 -> ●登記名義人住所
BK26: 氏 名 | BO26: =基本入力!AH103 -> ●登記名義人 | CI26: 氏 名 | CM26: =基本入力!AH103 -> ●登記名義人
B29: 依頼者甲は、この契約書および一般媒介契約約款により、別表に表示する不動産(目的物件)に関する売買(交換)の媒介を宅地建物取引業者乙に依頼し、乙はこれを承諾します。
BI31: 所在地 | BK31: =基本入力!J24&基本入力!AB24&基本入力!AD24&基本入力!AG24&基本入力!AJ24 -> 練馬区高松3丁目 ●番地●
AH32: =基本入力!F70 -> 令和 | AL32: =IF(基本入力!I70=0,"",基本入力!I70) -> 8 | AN32: 年 | AP32: =IF(基本入力!M70=0,"",基本入力!M70) | AR32: 月 | AT32: =IF(基本入力!Q70=0,"",基本入力!Q70) | AV32: 日
B35: 甲 | D35: ・ | E35: 依 頼 者 | N35: 住 所
BI36: 目 的 物 件 の 表 示 | BK36: 土 地 | BM36: 実 測 | CA36: ㎡ | CC36: 地 目 | CE36: □ | CF36: 宅地・ | CI36: □ | CJ36: 田・ | CL36: □ | CM36: 畑・ | CO36: 権利内容
CQ37: □ | CR37: 所有権 ・ | CW37: □ | CX37: 借地権
N38: 氏 名 | CE38: □ | CF38: 山林・ | CI38: □ | CJ38: 雑種地・
AW39: ㊞ | BM39: 公 簿 | CA39: ㎡
CE40: □ | CF40: その他 | CJ40: （ | CN40: ）
B41: 乙 | D41: ・ | E41: 宅地建物取引業者 | N41: 商号（名称） | X41: =重説!H30 -> 東京マンション株式会社
BK42: 建 物 | BM42: 建 築 面 積 | CA42: ㎡ | CC42: 種類 | CO42: 構造 | DC42: 造
N43: 代表者 | X43: =重説!H32 -> 代表取締役 髙橋 正臣
AW44: ㊞ | CV44: 葺 | DB44: 階建
N45: 主たる事務所の所在地 | X45: =重説!H24&" "&重説!H26 -> 東京都新宿区西新宿二丁目6番1号 新宿住友ビル19階
BM46: 延面積 | CA46: ㎡ | CC46: 間取り
N47: 免許証番号 | X47: =重説!H20 -> 国土交通大臣 | AF47: =重説!O20 -> (3) | AH47: 第 | AJ47: =重説!S20 -> 8684 | AO47: 号
B50: 1 | D50: 依頼する乙以外の宅地建物取引業者 | BK50: マンション | BM50: 名 称 | BR50: =基本入力!AB13 -> 0 | CH50: 構 造 | CM50: =基本入力!Q32 -> ●鉄筋コンクリート造1階建
E52: （商号または名称） | BR52: =基本入力!AH32 -> ● | BY52: 階 | CA52: =基本入力!AS13 -> ● | CE52: 号室 | CH52: タイプ | CM52: =基本入力!AJ15 -> ● | CV52: =基本入力!AL15 -> ＬＤＫ
E54: （主たる事務所の所在地） | BM54: 専 有 面 積 | BU54: 登記簿 | CA54: =基本入力!J34 -> 0 | CF54: ㎡ | CH54: 共有持分 | CM54: =IF(基本入力!AL42=0,"",基本入力!AL42) | CV54: 分の | CY54: =IF(基本入力!AT42=0,"",基本入力!AT42)
B56: 2 | D56: 甲の通知義務 | BU56: 壁芯 | CA56: =基本入力!AS15 -> - | CF56: ㎡
C58: 一 | E58: 甲は、この媒介契約の有効期間内に1に表示する宅地建物取引業者以外の宅地建物取引業者に重ねて目的物件の売買または交換の媒介または代理を依頼しようとするときは、乙に対して、その旨を通知する義務を負います。
BI59: 本 体 価 額 | BT59: 金 | BV59: =基本入力!AO70 -> 0 | CG59: 円 | CJ59: 備 考 | CL59: （その他の業務） 評価証明書、公課証明書取得に関する一切の権限 管理に係る調査報告書取得に関する一切の権限
C62: 二 | E62: 甲は、この媒介契約の有効期間内に、自ら発見した相手方と売買もしくは交換の契約を締結したとき、または乙以外の宅地建物取引業者の媒介もしくは代理によって売買もしくは交換の契約を締結させたときは、乙に対して、遅滞なくその旨を通知する義務を負います。 | BI62: 消費税額および 地方消費税額の合計額 | BT62: 金 | BV62: =基本入力!AA74 -> 0 | CG62: 円
C66: 三 | E66: 一および二の通知を怠った場合には、乙は、一般媒介契約約款の定めにより、甲に対して、費用の償還を請求することができます。 | BI66: 媒 介 価 額 | BT66: 総額 | BW66: =基本入力!AA70 -> 0 | CG66: 円
B69: 3 | D69: 成約に向けての乙の義務 | BI69: [ ただし、買い依頼に係る媒介契約については、次の別表を使用することとして差支えない。]
C71: 一 | E71: 乙は、契約の相手方との契約条件の調整等を行い、契約の成立に向けて積極的に努力します。
BI72: 希望する条件
C73: 二 | E73: 乙は、目的物件の売買又は交換の申込みがあったときは、甲に対し、遅滞なく、その旨を報告します。
BI74: 項 目 | BT74: 内 容 | CU74: 希 望 の 程 度
B75: 4 | D75: 媒介に係る乙の業務
BI76: 物 件 の 種 類 | CU76: 普通
D77: 乙は、3に掲げる義務を履行するとともに、次の業務を行います。
BI78: 価 額 | CU78: 普通
C79: 一 | E79: 乙は、甲に対し、目的物件を売買すべき価額または評価額について意見を述べるときは、その根拠を明らかにして説明を行います。
BI80: 広 さ ・ 間 取 り 等 | CU80: 普通
C82: 二 | E82: 甲が乙に目的物件の購入または取得を依頼した場合にあっては、乙は、甲に対し、目的物件の売買または交換の契約が成立するまでの間に、宅地建物取引士をして、宅地建物取引業法第35条に定める重要事項について、宅地建物取引士が記名押印した書面を交付して説明させます。 | BI82: 物 件 の 所 在 地 | CU82: 普通
BI85: そ の 他 の 条 件 （希望の程度も お書き下さい。）
C86: 三 | E86: 乙は、目的物件の売買または交換の契約が成立したときは、甲および甲の相手方に対し、遅滞なく、宅地建物取引業法第37条に定める書面を作成し、宅地建物取引士に当該書面に記名押印させた上で、これを交付します。
C90: 四 | E90: 乙は、甲に対し、登記、決済手続等の目的物件の引渡しに係る事務の補助を行います。 | BI90: 注） 「希望の程度」の欄には、「特に強い」、「やや強い」、「普通」等と記入すること。
B94: 一 般 媒 介 契 約 約 款 | BI94: （直接取引）
BI95: 第13条 | BM95: 一般媒介契約の有効期間内または有効期間の満了後2年以内に、甲が乙の紹介によって知った相手方と乙を排除して目的物件の売買または交換の契約を締結したときは、乙は、甲に対して、契約の成立に寄与した割合に応じた相当額の報酬を請求することができます。
B97: （目的）
B98: 第1条 | F98: この約款は、宅地または建物の売買または交換の一般媒介契約について、当事者が契約の締結に際して定めるべき事項および当事者が契約の履行に関して互いに遵守すべき事項を明らかにすることを目的とします。
BI99: （費用償還の請求）
BI100: 第14条 | BM100: 一般媒介契約の有効期間内に甲が乙に明示していない宅地建物取引業者に目的物件の売買または交換の媒介または代理を依頼し、これによって売買または交換の契約を成立させたときは、乙は、甲に対して、一般媒介契約の履行のために要した費用の償還を請求することができます。
B101: （当事者の表示と用語の定義）
B102: 第2条 | F102: この約款においては、媒介契約の当事者について、依頼者を「甲」、依頼を受ける宅地建物取引業者を「乙」と表示します。
E104: 2 | F104: この約款において、「一般媒介契約」とは、甲が依頼の目的である宅地または建物（以下「目的物件」といいます。）の売買または交換の媒介または代理を乙以外の宅地建物取引業者に重ねて依頼することができるものとする媒介契約をいいます。 | BL104: 2 | BM104: 前項の費用の額は、約定報酬額を超えることはできません。
BI106: （依頼者の通知義務）
B107: （目的物件の表示等） | BI107: 第15条 | BM107: 甲は、一般媒介契約の有効期間内に、自ら発見した相手方と目的物件の売買もしくは交換の契約を締結したとき、または乙以外の宅地建物取引業者の媒介もしくは代理によって目的物件の売買もしくは交換の契約を成立させたときは、乙に対して遅滞なくその旨を通知しなければなりません。
B108: 第3条 | F108: 目的物件を特定するために必要な表示および目的物件を売買すべき価額または交換すべき評価額（以下「媒介価額」といいます。）は、一般媒介契約書の別表に記載します。
B111: （重ねて依頼をする宅地建物取引業者の明示） | BL111: 2 | BM111: 甲が前項の通知を怠った場合において、乙が売買または交換の契約の成立後善意で甲のために一般媒介契約の事務の処理に要する費用を支出したときは、乙は、甲に対して、その費用の償還を請求することができます。
B112: 第4条 | F112: 甲は、目的物件の売買または交換の媒介または代理を乙以外の宅地建物取引業者に重ねて依頼するときは、その宅地建物取引業者を乙に明示しなければなりません。
BI114: （更新）
E115: 2 | F115: 一般媒介契約の締結時においてすでに依頼をしている宅地建物取引業者の商号または名称および主たる事務所の所在地は、一般媒介契約書に記載するものとし、その後において更に他の宅地建物取引業者に依頼をしようとするときは、甲は、その旨を乙に通知するものとします。 | BI115: 第16条 | BM115: 一般媒介契約の有効期間は、甲および乙の合意に基づき、更新することができます。
BL117: 2 | BM117: 有効期間の更新をしようとするときは、有効期間の満了に際して甲から乙に対し文書でその旨を申し出るものとします。
B119: （宅地建物取引業者の義務等） | BL119: 3 | BM119: 前2項の規定による有効期間の更新に当たり、甲乙間で一般媒介契約の内容について別段の合意がなされなかったときは、従前の契約と同一内容の契約が成立したものとみなします。
B120: 第5条 | F120: 乙は、次の事項を履行する義務を負います。
F122: 一 | H122: 契約の相手方を探索するとともに、契約の相手方との契約条件の調整等を行い、契約の成立に向けて積極的に努力すること | BI122: （契約の解除）
BI123: 第17条 | BM123: 甲または乙が一般媒介契約に定める義務の履行に関してその本旨に従った履行をしない場合には、その相手方は、相当の期間を定めて履行を催告し、その期間内に履行がないときは、一般媒介契約を解除することができます。
F125: 二 | H125: 目的物件の売買または交換の申込みがあったときは、甲に対して、遅滞なく、その旨を報告すること
BL126: 2 | BM126: 次のいずれかに該当する場合においては、甲は、一般媒介契約を解除することができます。
E127: 2 | F127: 乙は、前項に掲げる義務を履行するとともに、次の業務を行います。
BM128: 一 | BO128: 乙が一般媒介契約に係る業務について信義を旨とし誠実に遂行する義務に違反したとき
F129: 一 | H129: 媒介価額の決定に際し、甲に、その価額に関する意見を述べるときは、根拠を示して説明を行うこと
BM130: 二 | BO130: 乙が一般媒介契約に係る重要な事項について故意もしくは重過失により事実を告げず、または不実のことを告げる行為をしたとき
F131: 二 | H131: 甲が乙に目的物件の購入または取得を依頼した場合にあっては、甲に対して、目的物件の売買または交換の契約が成立するまでの間に、宅地建物取引士をして、宅地建物取引業法第35条に定める重要事項について、宅地建物取引士が記名押印した書面を交付して説明させること
BM133: 三 | BO133: 乙が宅地建物取引業に関して不正または著しく不当な行為をしたとき
F135: 三 | H135: 目的物件の売買または交換の契約が成立したときは、甲および甲の相手方に対して、遅滞なく、宅地建物取引業法第37条に定める書面を作成し、宅地建物取引士に当該書面に記名押印させた上で、これを交付すること | BI135: （反社会的勢力の排除）
BI136: 第18条 | BM136: 甲および乙は、それぞれ相手方に対し、次の事項を確約します。
F138: 四 | H138: 甲に対して、登記、決済手続等の目的物件の引渡しに係る事務の補助を行うこと | BM138: 一 | BO138: 自らが、暴力団、暴力団関係企業、総会屋もしくはこれらに準ずる者またはその構成員（以下これらを総称して「反社会的勢力」といいます。）ではないこと
F140: 五 | H140: その他一般媒介契約書に記載する業務を行うこと
BM141: 二 | BO141: 自らの役員（業務を執行する社員、取締役、執行役またはこれらに準ずる者をいいます。）が反社会的勢力ではないこと
B142: （媒介価額の変更の助言等）
B143: 第6条 | F143: 媒介価額が地価や物価の変動その他事情の変更によって不適当と認められるに至ったときは、乙は、甲に対して、媒介価額の変更について根拠を示して助言します。
BM144: 三 | BO144: 反社会的勢力に自己の名義を利用させ、一般媒介契約を締結するものでないこと
E146: 2 | F146: 甲は、媒介価額を変更しようとするときは、乙にその旨を通知します。この場合において、価額の変更が引上げであるとき（甲が乙に目的物件の購入または取得を依頼した場合にあっては、引下げであるとき） は、乙の承諾を要します。 | BM146: 四 | BO146: 一般媒介契約の有効期間内に、自らまたは第三者を利用して、次の行為をしないこと
BO148: イ | BQ148: 相手方に対する脅迫的な言動または暴力を用いる行為
E149: 3 | F149: 乙は、前項の承諾を拒否しようとするときは、その根拠を示さなければなりません。
BO150: ロ | BQ150: 偽計または威力を用いて相手方の業務を妨害し、または信用を毀損する行為
B151: （建物状況調査を実施する者のあっせん）
B152: 第7条 | F152: 乙は、この媒介契約において建物状況調査を実施する者のあっせんを行うこととした場合にあっては甲に対して、建物状況調査を実施する者をあっせんしなければなりません。 | BL152: 2 | BM152: 一般媒介契約の有効期間内に、甲または乙が次のいずれかに該当した場合には、その相手方は、何らの催告を要せずして、一般媒介契約を解除することができます。
B155: （有効期間） | BM155: 一 | BO155: 前項第一号または第二号の確約に反する申告をしたことが判明した場合
B156: 第8条 | F156: 一般媒介契約の有効期間は、3ヶ月を超えない範囲で、甲乙協議の上、定めます。
BM157: 二 | BO157: 前項第三号の確約に反し契約をしたことが判明した場合
B158: （指定流通機構への登録）
B159: 第9条 | F159: 乙は、この媒介契約において目的物件を指定流通機構に登録することとした場合にあっては、当該目的物件を一般媒介契約書に記載する指定流通機構に登録しなければなりません。 | BM159: 三 | BO159: 前項第四号の確約に反する行為をした場合
BL161: 3 | BM161: 乙が前項の規定により一般媒介契約を解除したときは、甲に対して、約定報酬額に相当する金額（すでに約定報酬の一部を受領している場合は、その額を除いた額とします。なお、この媒介に係る消費税額および地方消費税額の合計額に相当する額を除きます。）を違約金として請求することができます。
...

Sheet 売約定
A2: 報 酬 支 払 約 定 書
C8: 仲介者 | H8: =重説!H30 -> 東京マンション株式会社 | W8: と依頼者 | AB8: =VLOOKUP(基本入力!AE99,AY9:BN10,2,) -> ●登記名義人 | AQ8: は後記 | AY8: 中間省略に■があったら売主を変える
AY9: ■ | AZ9: =基本入力!AH109 -> ●登記名義人
C10: 不動産売買契約の仲介に対する報酬の支払いについて下記のとおり約定したので、その証として | AY10: □ | AZ10: =基本入力!AH103 -> ●登記名義人
C12: 本書２通を作成し、各自記名捺印のうえその１通を保有する。
C16: 記
C19: 売買代金 | N19: 金 | P19: =基本入力!AA70 -> 0 | AB19: 円也 | AE19: （内消費税 | AK19: =基本入力!AA74 -> 0 | AT19: 円也）
C22: 仲介報酬額 | N22: 金 | P22: =基本入力!E84 | AB22: 円也 | AE22: （内消費税 | AK22: =基本入力!E88 | AT22: 円也）
C25: 支払い時期 | L25: I | N25: 金 | P25: 0 | AB25: 円也 | AE25: （売買契約時）
L28: Ⅱ | N28: 金 | P28: =IFERROR(基本入力!E84-P25, "") | AB28: 円也 | AE28: （最終決済時）
C31: 支払方法 | N31: =基本入力!E93 -> 銀行振込 | AZ31: 銀行振込 | BD31: 報酬の支払い方法は、下記口座への振り込みとします。振込み手数料は依頼者負担とします。 ＜振込先＞ 「三井住友銀行 新宿西口支店（259） （普）2811658 トウキョウマンション（カ」
C34: 売主の手付金倍額支払により売買契約が解除された場合、もしくは、売主の責に帰すべき事由により売買契約が解除された場合、依頼者は上記の手数料の全額を支払うことを承諾します。この場合、手数料の残額の支払時期は売買契約が解除された時とします。ただし、解除条件または停止条件により売買契約が解除された場合を除きます。買主都合による解約の場合、売主は手数料を支払いません。
AZ39: 現金払い | BD39: 現金でお支払い頂く場合は必ず東京マンション本社で受渡をお願い致します。東京マンション本社以外での現金の受渡は出来ません。また、小切手等、現金以外での支払いは出来ませんので、ご了承ください。
C41: =IF(N31="","",VLOOKUP(N31,AZ31:CW46,5,)) -> 報酬の支払い方法は、下記口座への振り込みとします。振込み手数料は依頼者負担とします。 ＜振込先＞ 「三井住友銀行 新宿西口支店（259） （普）2811658 トウキョウマンション（カ」
AG48: =基本入力!F70 -> 令和 | AK48: =IF(基本入力!I70=0,"",基本入力!I70) -> 8 | AM48: 年 | AO48: =IF(基本入力!M70=0,"",基本入力!M70) | AQ48: 月 | AS48: =IF(基本入力!Q70=0,"",基本入力!Q70) | AU48: 日
C51: ＜仲介者＞ | I51: 商号（名称） | T51: =重説!H30 -> 東京マンション株式会社
I53: 代表者 | T53: =重説!H32 -> 代表取締役 髙橋 正臣 | AQ53: ㊞
I55: 主たる事務所の所在地 | T55: =重説!H24&" "&重説!H26 -> 東京都新宿区西新宿二丁目6番1号 新宿住友ビル19階
I57: 免許番号 | T57: =重説!H20 -> 国土交通大臣 | AC57: =重説!O20 -> (3) | AE57: 第 | AG57: =重説!S20 -> 8684 | AL57: 号
I59: 免許年月日 | T59: =重説!H22 -> 令和 | X59: =重説!L22 -> 6 | Z59: 年 | AB59: =重説!P22 -> 10 | AD59: 月 | AF59: =重説!T22 -> 2 | AH59: 日
C62: ＜依頼者＞
H63: 住所
H66: 氏名 | AT66: ㊞
A69: 【物件の表示】
C72: 所在地 | H72: =基本入力!F15&基本入力!J15&基本入力!N15&基本入力!X15&基本入力!AB15&" (住居表示）" -> 東京都練馬区高松3丁目 ●番●-●号 (住居表示）
C75: 物件名 | H75: =基本入力!AB13 -> 0 | AK75: =基本入力!AS13 -> ● | AQ75: 号室

Sheet 業務委託料
K2: 業務委託料 | Y2: 支払約定書
C8: 受託者 | H8: =重説!H30 -> 東京マンション株式会社 | W8: と委託者 | AB8: =基本入力!AH109 -> ●登記名義人 | AQ8: は後記
C10: 不動産に対する | J10: =K2 -> 業務委託料 | P10: の支払いについて下記のとおり約定したので、その証として本書２通を作成し、
C12: 各自記名捺印のうえその１通を保有する。
C16: 記
C19: =K2 -> 業務委託料 | N19: 金 | AB19: 円也 | AE19: （内消費税 | AK19: =P19-ROUNDUP(P19/1.1,0) -> 0 | AT19: 円也）
C22: 支払い時期 | N22: 後記不動産引渡日とします。
C25: 支払方法 | N25: 銀行振込 | AZ25: 銀行振込 | BD25: 本書に定めの無い事項については、原契約に基づくものとする。 | BR25: =K2 -> 業務委託料 | BY25: の支払い方法は、下記口座 | CM25: への振り込みとします。振込み手数料は依頼者負担とします。 ＜振込先＞ 「三井住友銀行 新宿西口支店（259） （普）2811658 トウキョウマンション（カ」
C28: 特約事項
C30: =IF(N25="","",VLOOKUP(N25,AZ25:CW40,5,)) -> 本書に定めの無い事項については、原契約に基づくものとする。 | AE30: =IF(N25="","",VLOOKUP(N25,AZ25:CW40,19,)) -> 業務委託料 | AK30: =IF(N25="","",VLOOKUP(N25,AZ25:CW40,26,)) -> の支払い方法は、下記口座
C32: =IF(N25="","",VLOOKUP(N25,AZ25:CW40,40,)) -> への振り込みとします。振込み手数料は依頼者負担とします。 ＜振込先＞ 「三井住友銀行 新宿西口支店（259） （普）2811658 トウキョウマンション（カ」
AZ33: 現金払い | CM33: 現金でお支払い頂く場合は必ず東京マンション本社で受渡をお願い致します。東京マンション本社以外での現金の受渡は出来ません。また、小切手等、現金以外での支払いは出来ませんので、ご了承ください。
AG42: =基本入力!F70 -> 令和 | AK42: =IF(基本入力!I70=0,"",基本入力!I70) -> 8 | AM42: 年 | AO42: =IF(基本入力!M70=0,"",基本入力!M70) | AQ42: 月 | AS42: =IF(基本入力!Q70=0,"",基本入力!Q70) | AU42: 日
C45: ＜受託者＞ | I45: 商号（名称） | T45: =重説!H30 -> 東京マンション株式会社 | AT45: ㊞
I47: 代表者 | T47: =重説!H32 -> 代表取締役 髙橋 正臣
I49: 主たる事務所の所在地 | T49: =重説!H24&" "&重説!H26 -> 東京都新宿区西新宿二丁目6番1号 新宿住友ビル19階
I51: 免許番号 | T51: =重説!H20 -> 国土交通大臣 | AC51: =重説!O20 -> (3) | AE51: 第 | AG51: =重説!S20 -> 8684 | AL51: 号
I53: 免許年月日 | T53: =重説!H22 -> 令和 | X53: =重説!L22 -> 6 | Z53: 年 | AB53: =重説!P22 -> 10 | AD53: 月 | AF53: =重説!T22 -> 2 | AH53: 日
C56: ＜委託者＞
H57: 住所
H60: 氏名 | AT60: ㊞
A63: 【物件の表示】
C65: 所在地 | H65: =基本入力!F15&基本入力!J15&基本入力!N15&基本入力!X15&基本入力!AB15&" (住居表示）" -> 東京都練馬区高松3丁目 ●番●-●号 (住居表示）
C68: 物件名 | H68: =基本入力!AB13 -> 0 | AK68: =基本入力!AS13 -> ● | AQ68: 号室

Sheet 買約定
A2: 報 酬 支 払 約 定 書
C8: 仲介者 | H8: =重説!H30 -> 東京マンション株式会社 | W8: と依頼者 | AB8: =基本入力!F13 -> ●買主太郎 | AQ8: は後記
C10: 不動産売買契約の仲介に対する報酬の支払いについて下記のとおり約定したので、その証として
C12: 本書２通を作成し、各自記名捺印のうえその１通を保有する。
C16: 記
C19: 売買代金 | N19: 金 | P19: =基本入力!AA70 -> 0 | AB19: 円也 | AE19: （内消費税 | AK19: =基本入力!AA74 -> 0 | AT19: 円也）
C22: 仲介報酬額 | N22: 金 | P22: =基本入力!M84 -> 66000 | AB22: 円也 | AE22: （内消費税 | AK22: =基本入力!M88 -> 6000 | AT22: 円也）
C25: 支払い時期 | L25: Ⅱ | N25: 金 | P25: 0 | AB25: 円也 | AE25: （売買契約時）
L28: Ⅱ | N28: 金 | P28: =IFERROR(基本入力!M84-P25, "") -> 66000 | AB28: 円也 | AE28: （最終決済時）
C31: 支払方法 | N31: =基本入力!M93 -> 銀行振込 | AZ31: 銀行振込 | BD31: 報酬の支払い方法は、下記口座への振り込みとします。振込み手数料は依頼者負担とします。 ＜振込先＞ 「三井住友銀行 新宿西口支店（259） （普）2811658 トウキョウマンション（カ」
C34: 買主の手付金放棄、もしくは、買主の責に帰すべき事由により売買契約が解除された場合、依頼者は上記の手数料の全額を支払うことを承諾します。この場合、手数料の残額の支払時期は売買契約が解除された時とします。ただし、解除条件または停止条件により売買契約が解除された場合を除きます。
AZ39: 現金払い | BD39: 現金でお支払い頂く場合は必ず東京マンション本社で受渡をお願い致します。東京マンション本社以外での現金の受渡は出来ません。また、小切手等、現金以外での支払いは出来ませんので、ご了承ください。
C41: =IF(N31="","",VLOOKUP(N31,AZ31:CW46,5,)) -> 報酬の支払い方法は、下記口座への振り込みとします。振込み手数料は依頼者負担とします。 ＜振込先＞ 「三井住友銀行 新宿西口支店（259） （普）2811658 トウキョウマンション（カ」
AG48: =基本入力!F70 -> 令和 | AK48: =IF(基本入力!I70=0,"",基本入力!I70) -> 8 | AM48: 年 | AO48: =IF(基本入力!M70=0,"",基本入力!M70) | AQ48: 月 | AS48: =IF(基本入力!Q70=0,"",基本入力!Q70) | AU48: 日
C51: ＜仲介者＞ | I51: 商号（名称） | T51: =重説!H30 -> 東京マンション株式会社
I53: 代表者 | T53: =重説!H32 -> 代表取締役 髙橋 正臣 | AQ53: ㊞
I55: 主たる事務所の所在地 | T55: =重説!H24&" "&重説!H26 -> 東京都新宿区西新宿二丁目6番1号 新宿住友ビル19階
I57: 免許番号 | T57: =重説!H20 -> 国土交通大臣 | AC57: =重説!O20 -> (3) | AE57: 第 | AG57: =重説!S20 -> 8684 | AL57: 号
I59: 免許年月日 | T59: =重説!H22 -> 令和 | X59: =重説!L22 -> 6 | Z59: 年 | AB59: =重説!P22 -> 10 | AD59: 月 | AF59: =重説!T22 -> 2 | AH59: 日
C62: ＜依頼者＞
H63: 住所
H66: 氏名 | AT66: ㊞
A69: 【物件の表示】
C72: 所在地 | H72: =基本入力!F15&基本入力!J15&基本入力!N15&基本入力!X15&基本入力!AB15&" (住居表示）" -> 東京都練馬区高松3丁目 ●番●-●号 (住居表示）
C75: 物件名 | H75: =基本入力!AB13 -> 0 | AK75: =基本入力!AS13 -> ● | AQ75: 号室

Sheet 覚書 (仲手値引)
A2: 覚 書
B7: 買主（甲） | G7: =基本入力!F13 -> ●買主太郎 | X7: と仲介（乙） | AD7: =重説!H30 -> 東京マンション株式会社 | AU7: は、
B9: 令和 | E9: =IF(基本入力!I70=0,"",基本入力!I70) -> 8 | H9: 年 | J9: =IF(基本入力!M70=0,"",基本入力!M70) | M9: 月 | O9: =IF(基本入力!Q70=0,"",基本入力!Q70) | R9: 日付の | U9: 「 | V9: =基本入力!AB13&基本入力!AS13&"号室" -> ●号室 | AO9: 」 | AP9: （以下「本物件」
B11: という）の売買契約（以下「原契約」という）に関し、下記のとおり合意しました。
B13: その証として本覚書弐通を作成し、それぞれが壱通ずつを所持します。
B17: 記
C21: 第1条
D23: 乙および甲は、本物件の仲介手数料を、正規手数料 | AC23: =基本入力!AK83 -> 66000 | AJ23: 円 | AL23: から | AO23: =基本入力!M86 -> 0 | AV23: 円
D25: 減額して、 | J25: =基本入力!M84 -> 66000 | Q25: 円 | S25: とします。
C28: 第2条
D30: 乙および甲は、本覚書に記載の仲介手数料について、理由の如何を問わず代金の増額・減額請求、その他
D32: 一切の意義申し立てをしないものとします。
C35: 第3条
D37: 甲は、本覚書の内容について、理由の如何を問わず他の第三者（税務署等の申告を除く）に対して漏洩しない
D39: ものとし、万一第三者に告知した場合、それにより生じた紛争・損害については甲の責任と負担で処理すること
D41: とし、乙に一切の迷惑をかけず何らの請求をしないものとします。
C44: 第4条
D46: 本覚書に定めのない事項については、全て原契約の各条項に従うものとします。
AU48: 以上
B58: 買 主 | I58: 甲 | L58: 住所
L61: 氏名 | AU61: ㊞
B65: 仲 介 | I65: 乙 | L65: 住所 | O65: 東京都新宿区西新宿二丁目6番1号 新宿住友ビル19階
L68: 氏名 | O68: 東京マンション株式会社 | AU68: ㊞
A71: 【物件の表示】
C74: 所在地 | H74: =基本入力!F15&基本入力!J15&基本入力!N15&基本入力!X15&基本入力!AB15&" (住居表示）" -> 東京都練馬区高松3丁目 ●番●-●号 (住居表示）
C77: 物件名 | H77: =基本入力!AB13 -> 0 | AK77: =基本入力!AS13 -> ● | AQ77: 号室

Sheet 鍵交換確認書
AG3: 令和 | AJ3: =IF(基本入力!I70=0,"",基本入力!I70) -> 8 | AL3: 年 | AN3: =IF(基本入力!M70=0,"",基本入力!M70) | AP3: 月 | AR3: =IF(基本入力!Q70=0,"",基本入力!Q70) | AT3: 日
C6: 鍵交換確認書
Z11: 東京マンション株式会社
Z13: 東京都新宿区西新宿二丁目6番1号 新宿住友ビル19階
Z15: TEL. | AC15: 03-3789-1111 | AK15: FAX. | AN15: 03-3789-2222
Z18: =基本入力!F15&基本入力!J15&基本入力!N15&基本入力!X15&基本入力!AB15&" (住居表示）" -> 東京都練馬区高松3丁目 ●番●-●号 (住居表示）
Z20: =基本入力!AB13 -> 0 | AO20: =基本入力!AS13 -> ● | AT20: 号室
B24: 1. | D24: 鍵交換費用詳細
D27: 鍵穴 | L27: 1箇所 | T27: （3本） | AB27: 33000 | AJ27: 円
L31: 2箇所 | T31: （6本） | AB31: 38500 | AJ31: 円
D37: オートロック | L37: 有 | T37: 玄関扉とオートロックの連動を希望する
L41: 無 | AA41: はい（+5,500円）
AA45: いいえ
D51: 追加の鍵 | L51: 有 | U51: 5,500円/1本 | AE51: 本 | AJ51: 円
L55: 無
D62: 合計 | L62: 本 | S62: 円
B67: 2. | E67: オートロック連動キーをご希望の場合には、最終決済日（引渡日）より
E69: 設置まで最大2ヶ月ほど時間を要する場合があります。
B73: 3. | E73: 備考
G79: 上記の内容を確認しました。
AQ86: ㊞

Sheet 領収証
D4: 領収証
D12: =基本入力!F13 -> ●買主太郎 | Z12: 様
AF13: 〒163-0219
AF15: =重説!H24&" "&重説!H26 -> 東京都新宿区西新宿二丁目6番1号 新宿住友ビル19階
AF17: =重説!H30 -> 東京マンション株式会社
AF19: TEL. | AH19: =重説!H44&"-"&重説!N44&"-"&重説!T44 -> 03-3789-1111 | AQ19: FAX. | AS19: 03-3789-2222
BE22: 契約金額 | BU22: 印紙税
AV24: 印紙貼付 | BE24: １千万円を超え５千万円以下のもの | BU24: 10000円
BE26: ５千万円を超え １億円以下のもの | BU26: 30000円
D28: 合計金額 | H28: =IF(基本入力!AA70<=50000000,10000,IF(基本入力!AA70<=100000000,30000,IF(基本入力!AA70<=500000000,60000,IF(基本入力!AA70>500000000,"手入力")))) -> 10000 | BE28: １億円を超え ５億円以下のもの | BU28: 60000円
D49: 収入印紙代として
W52: =基本入力!F70 -> 令和 | AA52: =IF(基本入力!I70=0,"",基本入力!I70) -> 8 | AC52: 年 | AE52: =IF(基本入力!M70=0,"",基本入力!M70) | AG52: 月 | AI52: =IF(基本入力!Q70=0,"",基本入力!Q70) | AK52: 日 | AM52: 上記正に領収いたしました
D81: =重説!H30 -> 東京マンション株式会社
D83: =AF13 -> 〒163-0219
AJ84: TEL. | AM84: =重説!H44&"-"&重説!N44&"-"&重説!T44 -> 03-3789-1111
D85: =重説!H24&" "&重説!H26 -> 東京都新宿区西新宿二丁目6番1号 新宿住友ビル19階
AJ86: FAX. | AM86: =AS19 -> 03-3789-2222

Sheet 引越までの流れ　融資
D2: お客様名： | K2: =基本入力!F13 -> ●買主太郎 | AE2: 様
D6: 物件名： | K6: =基本入力!AB13 -> 0 | AK6: =基本入力!AS13 -> ● | AO6: 号室 | BH6: 住居表示： | BO6: =基本入力!F15&基本入力!J15&基本入力!N15&基本入力!X15&基本入力!AB15 -> 東京都練馬区高松3丁目 ●番●-●号
D11: 営業担当がご案内致します | BH11: 履行担当に引き継ぎます
D15: 契約 | V15: 本審査 | AO15: ローン内定 | BH15: 金銭消費賃貸契約 | BZ15: 決済（引渡し） | CS15: 引越し
D20: 日付： | V20: 提出期間： | AF20: ～ | AO20: 日付： | BH20: 日付： | BZ20: 日付：
G21: =基本入力!F70 -> 令和 | J21: =IF(基本入力!I70=0,"",基本入力!I70) -> 8 | L21: 年 | M21: =IF(基本入力!M70=0,"",基本入力!M70) | O21: 月 | P21: =IF(基本入力!Q70=0,"",基本入力!Q70) | R21: 日 | AR21: =基本入力!O115 -> 令和 | AU21: =IF(基本入力!R115=0,"",基本入力!R115) -> 8 | AW21: 年 | AX21: =IF(基本入力!V115=0,"",基本入力!V115) | AZ21: 月 | BA21: =IF(基本入力!Z115=0,"",基本入力!Z115) | BC21: 日まで | CC21: =基本入力!O119 -> 令和 | CF21: =IF(基本入力!R119=0,"",基本入力!R119) -> 8 | CH21: 年 | CI21: =IF(基本入力!V119=0,"",基本入力!V119) | CK21: 月 | CL21: =IF(基本入力!Z119=0,"",基本入力!Z119) | CN21: 日
BH22: 時間：
B24: 必要書類 | D24: ☑ | E24: 手付金 | K24: =基本入力!AA72 -> 0 | Q24: 円 | V24: □ | W24: 実印 | BH24: □ | BI24: 実印 | BZ24: □ | CA24: 実印
D26: ☑ | E26: 収入印紙代 | K26: =領収証!H28 -> 10000 | Q26: 円 | V26: □ | W26: 住民票 | AK26: 通 | BH26: □ | BI26: 身分証明書 | BZ26: □ | CA26: 通帳（自己資金）※諸費用含む
D28: ☑ | E28: 身分証明書 | V28: (※世帯全員分、本籍地省略、続柄有) | BH28: □ | BI28: 住民票（新住所のもの） | BZ28: □ | CA28: 身分証明書
D30: ☑ | E30: 印鑑（実印） | V30: □ | W30: 印鑑証明書 | AK30: 通 | BH30: （世帯全員分、本籍地省略、続柄有、マイナンバー省略） | BZ30: □ | CA30: 通帳届出印
D32: （※印鑑登録をしていない場合、契約後に印鑑登録をお願い致します。） | V32: □ | W32: 課税証明書（ 年分） | AG32: 各 | AK32: 通 | BZ32: （※管理費・修繕積立金等の引き落し口座を決めます。住宅ローンと違う口座にする場合はその通帳と届出印をご持参下さい。）
BH33: □ | BI33: 印鑑証明書（新住所のもの）
V34: □ | W34: 納税証明書（ 年分） | AG34: 各 | AK34: 通
BH35: □ | BI35: 通帳及び通帳届出印
W36: (※その1、その2）
BH37: (※通帳は金消契約時に作成出来ます）
V38: □ | W38: 免許証・保険証
BH39: □ | BI39: 印紙（ 円× ・ 円× ）
V40: □ | W40: 収入証明（源泉・給与明細・給与証明）
BH41: (※実際に印紙をご購入の上､ご持参下さい）
V42: □ | W42: 銀行審査書類
BH43: □ | BI43: 売買契約書の原本
B46: お客様の行動 | D46: □ | E46: 重要事項説明 | V46: □ | W46: 住民票・印鑑証明書取得 | AO46: □ | AP46: 住民票異動・書類取得 | BH46: □ | BI46: 銀行とのローン契約 | BZ46: □ | CA46: 司法書士による登記書類確認 | CS46: ＜引越しのお手続き（東京23区内）＞ 【東京電力】 ※Webから申込 ※詳細はパンフレットをご参照下さい ＴＥＬ：０１２０－９９５－００５ 【水道】 ※電話にて申込 ＴＥＬ：０３－５３２６－１１００ 【東京ガス】 ※Webから申込 ※詳細はパンフレットをご参照下さい ※開栓は立会いが必要です ＴＥＬ：０５７０－００２２３０ ※ 武蔵野市、昭島市、羽村市、檜原村は各市町村役場にて手続きできます。
D48: □ | E48: 売買契約書類の読み合わせ | V48: ※市町村役所にてご取得下さい。 その年の1月1日に居住していた場合の役所です。 | AO48: 購入物件の住所に住民票を異動し、新住所にて住民票や印鑑証明をご取得下さい。 ①現住所の市区町村役所にて除籍 ②新住所の市区町村役所にて、転入・上記書類取得 | BZ48: □ | CA48: 登記書類への記名・押印
D50: □ | E50: 契約関係書類への記名・押印 | BZ50: □ | CA50: 住宅ローンの実行
V51: □ | W51: 課税・納税証明書
D52: □ | E52: 手付金の授受 | BZ52: □ | CA52: 残代金・清算金等の支払い
V53: ※市町村役所・税務署にてご取得下さい。
BZ54: □ | CA54: 登記費用・仲介手数料等の支払い
V55: □ | W55: 源泉・給与明細・給与証明
BZ56: □ | CA56: 物件引渡
V57: ※お持ちでなければ、勤務先の経理部門からご取得下さい。
AO58: □ | AP58: 金消契約・決済日設定 | BZ58: □ | CA58: 火災保険申込
AO60: 金消日： | AS60: 平日9：00～16：00
AS61: 上記の間で2時間程度
AO62: 決済日： | AS62: 平日9：00～13：00
AS63: 上記の間で２2時間程度
B64: 備考 | D64: ※諸費用の試算書を作成致します。 （諸費用については、金融機関や司法書士・保険プラン・引渡日等により変更があることを予めご承知おき下さい。） ※火災保険：当社プランよりお選び下さい。（提携先：東京海上日動火災保険） | V64: ※銀行から（追加）提出書類を請求される事があります。すばやい対応をお願い致します。 | AO64: ※除籍・転入する際は、市区町村にて、必ず「引越ししました」とお伝え下さい。 ※銀行との契約日（金銭消費貸借契約日）は、1週間前まででないと予約が取れない可能性があります。早期のご予約をお願い致します。 | BH64: ※銀行とお客様との契約となりますので当社は立会いを行いませんが、ご持参いただくもの等、事前にご案内させていただきます。 ※銀行の予約が立込んでおりますので、時間厳守でお願い致します。 | BZ64: ※お客様・当社・売主・司法書士立会いで登記書類記名押印・残代金等の支払・物件の引渡しを行います。 ※銀行の予約が立込んでおりますので、時間厳守でお願い致します。 ※決済日前日までに、自己資金を決済通帳にご入金下さい。 ※決済前日までに火災保険の加入プランを確定していただきます。 | CS64: ※引越しの際、上下左右に挨拶することをお勧めします。 ※物件によっては管理人の提出書類があります。
V80: =重説!H30 -> 東京マンション株式会社 | BR80: =基本入力!F70 -> 令和 | BU80: =IF(基本入力!I70=0,"",基本入力!I70) -> 8 | BW80: 年 | BX80: =IF(基本入力!M70=0,"",基本入力!M70) | BZ80: 月 | CB80: =IF(基本入力!Q70=0,"",基本入力!Q70) | CD80: 日
V84: 代表電話番号： | AE84: =重説!H44&"-"&重説!N44&"-"&重説!T44 -> 03-3789-1111
V86: 業務部直通番号： | AE86: 03-6911-2800
V88: 〒163-0219 | AB88: =重説!H24&" "&重説!H26 -> 東京都新宿区西新宿二丁目6番1号 新宿住友ビル19階 | BR88: 氏 名
DE89: ㊞

Sheet 現金
E2: お客様名： | L2: =基本入力!F13 -> ●買主太郎 | AF2: 様
E6: 物件名： | L6: =基本入力!AB13 -> 0 | AL6: =基本入力!AS13 -> ● | AP6: 号室 | BI6: 住居表示： | BP6: =基本入力!F15&基本入力!J15&基本入力!N15&基本入力!X15&基本入力!AB15 -> 東京都練馬区高松3丁目 ●番●-●号
E11: 営業担当がご案内致します | BI11: 決済日当日は、決済業務担当に引き継ぐ場合がございます
E15: 契約 | W15: 本審査 | AP15: ローン内定 | BI15: 金銭消費賃貸契約 | CA15: 決済（引渡し） | CT15: 引越し
E20: 日付： | W20: 提出期間： | AG20: ～ | BI20: 日付： | CA20: 日付：
H21: =基本入力!F70 -> 令和 | K21: =IF(基本入力!I70=0,"",基本入力!I70) -> 8 | M21: 年 | N21: =IF(基本入力!M70=0,"",基本入力!M70) | P21: 月 | Q21: =IF(基本入力!Q70=0,"",基本入力!Q70) | S21: 日 | CD21: =基本入力!O119 -> 令和 | CG21: =IF(基本入力!R119=0,"",基本入力!R119) -> 8 | CI21: 年 | CJ21: =IF(基本入力!V119=0,"",基本入力!V119) | CL21: 月 | CM21: =IF(基本入力!Z119=0,"",基本入力!Z119) | CO21: 日
BI22: 時間：
C24: 必要書類 | E24: ☑ | F24: 手付金 | L24: =基本入力!AA72 -> 0 | R24: 円 | W24: □ | X24: 実印 | BI24: □ | BJ24: 実印 | CA24: □ | CB24: 実印
E26: ☑ | F26: 収入印紙代 | L26: =領収証!H28 -> 10000 | R26: 円 | W26: □ | X26: 住民票 | AL26: 通 | BI26: □ | BJ26: 身分証明書 | CA26: □ | CB26: 通帳（自己資金）※諸費用含む
E28: ☑ | F28: 身分証明書 | W28: (※世帯全員分、本籍地省略、続柄有) | BI28: □ | BJ28: 住民票（新住所のもの） | CA28: □ | CB28: 身分証明書
E30: ☑ | F30: 印鑑（実印） | W30: □ | X30: 印鑑証明書 | AL30: 通 | BI30: （世帯全員分、本籍地省略、続柄有、マイナンバー省略） | CA30: □ | CB30: 通帳届出印
W32: □ | X32: 課税証明書（ 年分） | AH32: 各 | AL32: 通 | CA32: （※管理費・修繕積立金等の引き落し口座を決めます。住宅ローンと違う口座にする場合はその通帳と届出印をご持参下さい。）
BI33: □ | BJ33: 印鑑証明書（新住所のもの）
W34: □ | X34: 納税証明書（ 年分） | AH34: 各 | AL34: 通
BI35: □ | BJ35: 通帳及び通帳届出印
X36: (※その1、その2）
BI37: (※通帳は金消契約時に作成出来ます）
W38: □ | X38: 免許証・保険証
BI39: □ | BJ39: 印紙（ 円× ・ 円× ）
W40: □ | X40: 収入証明（源泉・給与明細・給与証明）
BI41: (※実際に印紙をご購入の上､ご持参下さい）
W42: □ | X42: 銀行審査書類
BI43: □ | BJ43: 売買契約書の原本
C46: お客様の行動 | E46: □ | F46: 重要事項説明 | W46: □ | X46: 住民票・印鑑証明書取得 | AP46: □ | AQ46: 住民票異動・書類取得 | BI46: □ | BJ46: 銀行とのローン契約 | CA46: □ | CB46: 司法書士による登記書類確認 | CT46: ＜引越しのお手続き（東京23区内）＞ 【東京電力】 ※Webから申込 ※詳細はパンフレットをご参照下さい ＴＥＬ：０１２０－９９５－００５ 【水道】 ※電話にて申込 ＴＥＬ：０３－５３２６－１１００ 【東京ガス】 ※Webから申込 ※詳細はパンフレットをご参照下さい ※開栓は立会いが必要です ＴＥＬ：０５７０－００２２３０ ※ 武蔵野市、昭島市、羽村市、檜原村は各市町村役場にて手続きできます。
E48: □ | F48: 売買契約書類の読み合わせ | W48: ※市町村役所にてご取得下さい。 その年の1月1日に居住していた場合の役所です。 | AP48: 購入物件の住所に住民票を異動し、新住所にて住民票や印鑑証明をご取得下さい。 ①現住所の市区町村役所にて除籍 ②新住所の市区町村役所にて、転入・上記書類取得 | CA48: □ | CB48: 登記書類への記名・押印
E50: □ | F50: 契約関係書類への記名・押印 | CA50: □ | CB50: 住宅ローンの実行
W51: □ | X51: 課税・納税証明書
E52: □ | F52: 手付金の授受 | CA52: □ | CB52: 残代金・清算金等の支払い
W53: ※市町村役所・税務署にてご取得下さい。
CA54: □ | CB54: 登記費用・仲介手数料等の支払い
W55: □ | X55: 源泉・給与明細・給与証明
CA56: □ | CB56: 物件引渡
W57: ※お持ちでなければ、勤務先の経理部門からご取得下さい。
AP58: □ | AQ58: 金消契約・決済日設定 | CA58: □ | CB58: 火災保険申込
AP60: 金消日： | AT60: 平日9：00～16：00
AT61: 上記の間で2時間程度
AP62: 決済日： | AT62: 平日9：00～13：00
AT63: 上記の間で２2時間程度
C64: 備考 | E64: ※諸費用の試算書を作成致します。 （諸費用については、金融機関や司法書士・保険プラン・引渡日等により変更があることを予めご承知おき下さい。） ※火災保険：当社プランよりお選び下さい。（提携先：東京海上日動火災保険） | W64: ※銀行から（追加）提出書類を請求される事があります。すばやい対応をお願い致します。 | AP64: ※除籍・転入する際は、市区町村にて、必ず「引越ししました」とお伝え下さい。 | BI64: ※銀行とお客様との契約となりますので当社は立会いを行いませんが、ご持参いただくもの等、事前にご案内させていただきます。 ※銀行の予約が立込んでおりますので、時間厳守でお願い致します。 ※この日までに火災保険の加入プランを確定していただきます。 | CA64: ※お客様・当社・売主・司法書士立会いで登記書類記名押印・残代金等の支払・物件の引渡しを行います。 ※銀行の予約が立込んでおりますので、時間厳守でお願い致します。 ※決済日前日までに、自己資金を決済通帳にご入金下さい。 | CT64: ※引越しの際、上下左右に挨拶することをお勧めします。 ※物件によっては管理人の提出書類があります。
W80: =重説!H30 -> 東京マンション株式会社 | BS80: =基本入力!F70 -> 令和 | BV80: =IF(基本入力!I70=0,"",基本入力!I70) -> 8 | BX80: 年 | BY80: =IF(基本入力!M70=0,"",基本入力!M70) | CA80: 月 | CC80: =IF(基本入力!Q70=0,"",基本入力!Q70) | CE80: 日
W84: 代表電話番号： | AF84: =重説!H44&"-"&重説!N44&"-"&重説!T44 -> 03-3789-1111
W86: 業務部直通番号： | AF86: 03-6911-2800
W88: 〒163-0219 | AC88: =重説!H24&" "&重説!H26 -> 東京都新宿区西新宿二丁目6番1号 新宿住友ビル19階 | BS88: 氏 名
DF89: ㊞

Sheet 印刷方法
A1: 原本
A2: ≪A3≫
A3: （両） | B3: 売契 1部（読み合わせ用：+買主の数）
A4: ​（片） | B4: 重説 3部
A5: （両） | B5: 媒介 2部 （売、買 ともに）
A6: ​（片） | B6: 引渡しの流れ 1部
A7: ​（片） | B7: 物件状況報告書 1部
A8: （片） | B8: 付帯設備表 1部
A10: ≪A4≫
A11: ​（片） | B11: 約定 2部
A12: ​​（片） | B12: 鍵 1部
A13: ​​（片） | B13: 印紙領収書 1部
A14: ​------------------------------------​-------​-------
A16: 資料（全て1部）
A17: ≪A3≫
A18: ​（片） | B18: ハザードマップ ※印付ける
A19: ​（片） | B19: 公図
A20: ​（片） | B20: 地積
A21: ​（片） | B21: 道路台帳
A22: （片） | B22: 長計（計画表のみ）
A24: ≪A4≫
A26: （片） | B26: 謄本（建物）
A27: （両） | B27: 謄本（土地） ※2up
A28: （片） | B28: 重調
A29: （両） | B29: 管理規約、使用細則
A30: （片） | B30: 評価証明書
A31: （片） | B31: 台帳記載事項証明
A32: （片） | B32: 東京カンテイ ※枚数によっては両面
A33: （片） | B33: 耐震診断報告書
A34: （片） | B34: 総会資料
A36: ​※その他資料についてはほどんどA4（片）
A38: ※未来のアフターはA3（片） →A4 2枚を2upでA3 1枚に印刷する

Sheet 取完
AR2: 45292 | BD2: ←決済日を入れる
C5: =基本入力!F70 -> 令和 | G5: =基本入力!I70 -> 8 | I5: 年 | K5: =基本入力!M70 -> 0 | M5: 月 | O5: =基本入力!Q70 -> 0 | Q5: 日 | S5: 付売買契約に基づき、売主は売買代金を買主より受領し、登記関係書類を買主に
C7: 交付した。これにより売主および買主は、下記物件の取引を完了したことを確認した。
C10: 売主 | G10: 住 所 | P10: =基本入力!AH105 -> ●登記名義人住所
G13: 氏 名 | P13: =基本入力!AH103 -> ●登記名義人 | AY13: ㊞
C17: 買主 | G17: 住 所
G20: 氏 名 | P20: =基本入力!F13 -> ●買主太郎 | AY20: ㊞
C24: 立会人
C26: =重説!H24&" "&重説!H26 -> 東京都新宿区西新宿二丁目6番1号 新宿住友ビル19階
C28: =重説!H30 -> 東京マンション株式会社
C30: 電話番号 | H30: =重説!H44&"-"&重説!N44&"-"&重説!T44 -> 03-3789-1111 | BE30: 決済日 | BN30: =AR2 -> 45292 | BW30: ←決済日（自動反映）
BE32: 決済月の日数 | BN32: =DAY(DATE(YEAR(BN30),MONTH(BN30)+1,0)) -> 31 | BW32: ※自動計算
C33: 1. 物件の表示
BE34: 年間日数 | BN34: =DATE(YEAR(BN30)+1,1,1)-DATE(YEAR(BN30),1,1) -> 366 | BW34: ※自動計算
C35: 物 件 名 | J35: =基本入力!AB13 -> 0 | AM35: =基本入力!AS13 -> ● | AS35: 号室
BE36: 月末までの日数 | BN36: =BN32-DAY(BN30)+1 -> 31 | BW36: ※自動計算
C38: 所 在 地 | J38: =基本入力!J24&基本入力!AB24&基本入力!AD24&基本入力!AG24&基本入力!AJ24 -> 練馬区高松3丁目 ●番地● | AS38: 登記簿 | BE38: 年末までの日数 | BN38: =DATEDIF(BN30,DATE(YEAR(BN30),12,31),"D")+1 -> 366 | BW38: ※自動計算
C42: 2. 確認事項
BE44: 年額正誤チェック
C45: （1）物件残代金 | M45: ='売契（業者）'!AG70 -> 0 | Z45: ①
BE46: =IF(AN52+AN54=AN50,"○","×") -> ○ | BJ46: ←売主負担額と買主負担額の合計が月額と合ってない場合は「×」と出ます
C48: （2）清算金明細
C50: １．固定資産税・都市計画税 | AE50: 合計年額 | AN50: =CR103 -> 0 | AV50: 円也
C52: 売主負担分 | J52: =AN50 -> 0 | Q52: 円 | S52: ÷ | V52: =BN34 -> 366 | Z52: 日 | AB52: × | AE52: =BN34-BN38 -> 0 | AI52: 日 | AK52: ＝ | AN52: =ROUND(J52/V52*AE52,0) -> 0 | AV52: 円也
C54: 買主負担分 | J54: =AN50 -> 0 | Q54: 円 | S54: ÷ | V54: =BN34 -> 366 | Z54: 日 | AB54: × | AE54: =BN38 -> 366 | AI54: 日 | AK54: ＝ | AN54: =ROUND(J54/V54*AE54,0) -> 0 | AV54: 円也 | AZ54: ②
C56: ※固定資産税・都市計画税は売主より支払いの為、買主清算とします。
BE57: 月額正誤チェック
C58: ※固定資産税・都市計画税の起算日は | R58: =IF(AR2="","",DATE(YEAR(AR2),1,1)) -> 45292 | V58: 43831 | Z58: としております。
BE59: =IF(AN62+AN64=AN60,"○","×") -> ○ | BJ59: ←売主負担額と買主負担額の合計が月額と合ってない場合は「×」と出ます
C60: ２．管理費・修繕積立金等 | AE60: 合計月額 | AN60: =重説!S311+重説!S334 -> 0 | AV60: 円也
C62: 売主負担分 | J62: =AN60 -> 0 | Q62: 円 | S62: ÷ | V62: =BN32 -> 31 | Z62: 日 | AB62: × | AE62: =BN32-BN36 -> 0 | AI62: 日 | AK62: ＝ | AN62: =ROUND(J62/V62*AE62,0) -> 0 | AV62: 円也
C64: 買主負担分 | J64: =AN60 -> 0 | Q64: 円 | S64: ÷ | V64: =BN32 -> 31 | Z64: 日 | AB64: × | AE64: =BN36 -> 31 | AI64: 日 | AK64: ＝ | AN64: =ROUND(J64/V64*AE64,0) -> 0 | AV64: 円也 | AZ64: ③
C66: 買主負担分 | J66: =AN60 -> 0 | Q66: 円 | U66: （ | V66: =IF(AR2="","",DATE(YEAR(AR2),1,1)) -> 45292 | AE66: 月分 | AI66: ） | AN66: =AN60 -> 0 | AV66: 円也 | AZ66: ④
C69: ３．その他
C71: （1）引渡鍵 | J71: 玄関ドア | U71: 本 | W71: NO
J73: オートロック
J75: 宅配BOXカード
J77: 集合ポスト
C80: （2）備 考
J83: 清算分 | S83: ② ＋ ③ ＋ ④ ＝ | AJ83: =AN54+AN64+AN66 -> 0 | AR83: 円也
B86: =基本入力!F13 -> ●買主太郎 | P86: 様から | S86: =基本入力!AH109 -> ●登記名義人 | AG86: 様へ | AJ86: =AJ83+M45 -> 0 | AR86: 円也を支払うものとする。
B89: ≪振込先≫
B91: 金融機関 | J91: 三井住友銀行 | AC91: 支店名 | AK91: 新宿西口支店
B93: 口座種別 | J93: 普通 | AC93: 口座番号 | AK93: 2811658
B95: 口座名義（カナ） | J95: トウキョウマンション（カ
B97: 口座名義（漢字） | J97: 東京マンション株式会社
CF102: 土地 | CG102: 持ち分 | CN102: 家屋 | CR102: 合計
CF103: 分子 | CH103: 固定資産税 | CJ103: 0.014 | CL103: =IFERROR(ROUNDDOWN(CG103/CG104*CI103*CJ103,0),0) -> 0 | CO103: 0.017 | CP103: =ROUNDDOWN(CN103*CO103,0) -> 0 | CR103: =SUM(CL:CL,CP:CP) -> 0
CF104: 分母 | CH104: 都市計画税 | CJ104: 0.003 | CL104: =IFERROR(ROUNDDOWN(CG103/CG104*CI104*CJ104*0.5,0),0) -> 0
CF106: 分子 | CH106: 固定資産税 | CJ106: 0.014 | CL106: =IFERROR(ROUNDDOWN(CG106/CG107*CI106*CJ106,0),0) -> 0
CF107: 分母 | CH107: 都市計画税 | CJ107: 0.003 | CL107: =IFERROR(ROUNDDOWN(CG106/CG107*CI107*CJ107*0.5,0),0) -> 0
CF109: 分子 | CH109: 固定資産税 | CJ109: 0.014 | CL109: =IFERROR(ROUNDDOWN(CG109/CG110*CI109*CJ109,0),0) -> 0
CF110: 分母 | CH110: 都市計画税 | CJ110: 0.003 | CL110: =IFERROR(ROUNDDOWN(CG109/CG110*CI110*CJ110*0.5,0),0) -> 0
CF112: 分子 | CH112: 固定資産税 | CJ112: 0.014 | CL112: =IFERROR(ROUNDDOWN(CG112/CG113*CI112*CJ112,0),0) -> 0
CF113: 分母 | CH113: 都市計画税 | CJ113: 0.003 | CL113: =IFERROR(ROUNDDOWN(CG112/CG113*CI113*CJ113*0.5,0),0) -> 0

Sheet 契約後処理リスト
A1: 物件名 | B1: =基本入力!AB13&" "&基本入力!AS13&基本入力!AV13 -> ●号室
B2: 項目
A3: □ | B3: 契約後スキャン
A4: □ | B4: サーバーの移動（契約書→決済管理）
A5: □ | B5: 各MAX 変更する（反響、案内、申込、決済管理（連絡先）、月別成績）
A6: □ | B6: 不動産成績（Excel） 入れる
A7: □ | B7: 鍵 現調 （鍵場所： いつ行く： ）
A8: □ | B8: いえらぶ 住所更新
A9: □ | B9: いくら不動産 登録
A10: □ | B10: プロポ成約 登録
A11: □ | B11: 火災保険 スプレットシート入力
A12: □ | B12: 火災保険 見積書
A13: □ | B13: LINEの登録名 変更 （【契約】へ変更する・契約のタグをつける）
A14: □ | B14: ネット掲載を落とす。R-DB、入稿。
A15: □ | B15: 契発/稟議書 提出
